Workbook
Name Slicer_ShipCountry: #N/A

Sheet EDA Q_1
B3: Average number of Orders per customers
L4: High repeat value customers by Total_sales
B6: Row Labels | C6: Count of OrderID
B7: ALFKI | C7: 6
B8: ANATR | C8: 4 | L8: CustomerID | M8: Sum of Total_sales
B9: ANTON | C9: 7 | L9: QUICK | M9: 110277.31
B10: AROUT | C10: 13 | L10: Grand Total | M10: 110277.31
B11: BERGS | C11: 18
B12: BLAUS | C12: 7
B13: BLONP | C13: 11
B14: BOLID | C14: 3
B15: BONAP | C15: 17
B16: BOTTM | C16: 14
B17: BSBEV | C17: 10
B18: CACTU | C18: 6
B19: CENTC | C19: 1
B20: CHOPS | C20: 8
B21: COMMI | C21: 5
B22: CONSH | C22: 3
... B96: Grand Total | C96: 830

Sheet EDA Q_2
E2: 2. How do customer order patterns vary by city or country
C6: Country / City | D6: Count of OrderID | F6: Country / City | G6: Sum of Total_sales
C7: Argentina | D7: 16 | F7: Argentina | G7: 8119.1
C8: Buenos Aires | D8: 16 | F8: Buenos Aires | G8: 8119.1
C9: Austria | D9: 40 | F9: Austria | G9: 128003.84
C10: Graz | D10: 30 | F10: Graz | G10: 104874.98
C11: Salzburg | D11: 10 | F11: Salzburg | G11: 23128.86
C12: Belgium | D12: 19 | F12: Belgium | G12: 33824.855
C13: Bruxelles | D13: 7 | F13: Bruxelles | G13: 9736.075
C14: Charleroi | D14: 12 | F14: Charleroi | G14: 24088.78
C15: Brazil | D15: 83 | F15: Brazil | G15: 106925.78
C16: Campinas | D16: 9 | F16: Campinas | G16: 8414.135
C17: Resende | D17: 9 | F17: Resende | G17: 6068.2
C18: Rio de Janeiro | D18: 34 | F18: Rio de Janeiro | G18: 51956.98
... C98: Grand Total | D98: 830 | F98: Grand Total | G98: 1265793

Sheet EDA Q_3
B3: 3. Can we cluster customers based on total spend, order count, and preferred categories?
D5: Customer Summary
B8: CustomerId | C8: Count of OrderID | D8: Sum of Total_revenue | E8: Preffered_Category | H8: Preffered_Category | I8: Count of CustomerId
B9: ALFKI | C9: 6 | D9: 4273 | E9: =_xlfn.XLOOKUP(B9,order_details[CustomerID],order_details[Category Name]) -> Produce | H9: Beverages | I9: 12
B10: ANATR | C10: 4 | D10: 1402.95 | E10: =_xlfn.XLOOKUP(B10,order_details[CustomerID],order_details[Category Name]) -> Dairy Products | H10: Condiments | I10: 11
B11: ANTON | C11: 7 | D11: 7023.9775 | E11: =_xlfn.XLOOKUP(B11,order_details[CustomerID],order_details[Category Name]) -> Dairy Products | H11: Confections | I11: 18
B12: AROUT | C12: 13 | D12: 13390.65 | E12: =_xlfn.XLOOKUP(B12,order_details[CustomerID],order_details[Category Name]) -> Beverages | H12: Dairy Products | I12: 15
B13: BERGS | C13: 18 | D13: 24927.577 | E13: =_xlfn.XLOOKUP(B13,order_details[CustomerID],order_details[Category Name]) -> Condiments | H13: Grains/Cereals | I13: 5
B14: BLAUS | C14: 7 | D14: 3239.8 | E14: =_xlfn.XLOOKUP(B14,order_details[CustomerID],order_details[Category Name]) -> Meat/Poultry | H14: Meat/Poultry | I14: 9
B15: BLONP | C15: 11 | D15: 18534.08 | E15: =_xlfn.XLOOKUP(B15,order_details[CustomerID],order_details[Category Name]) -> Meat/Poultry | H15: Produce | I15: 7
B16: BOLID | C16: 3 | D16: 4232.85 | E16: =_xlfn.XLOOKUP(B16,order_details[CustomerID],order_details[Category Name]) -> Condiments | H16: Seafood | I16: 12
B17: BONAP | C17: 17 | D17: 21963.253 | E17: =_xlfn.XLOOKUP(B17,order_details[CustomerID],order_details[Category Name]) -> Meat/Poultry | H17: (blank) | I17: 1
B18: BOTTM | C18: 14 | D18: 20801.6 | E18: =_xlfn.XLOOKUP(B18,order_details[CustomerID],order_details[Category Name]) -> Seafood | H18: Grand Total | I18: 90
B19: BSBEV | C19: 10 | D19: 6089.9 | E19: =_xlfn.XLOOKUP(B19,order_details[CustomerID],order_details[Category Name]) -> Condiments
B20: CACTU | C20: 6 | D20: 1814.8 | E20: =_xlfn.XLOOKUP(B20,order_details[CustomerID],order_details[Category Name]) -> Beverages
B21: CENTC | C21: 1 | D21: 100.8 | E21: =_xlfn.XLOOKUP(B21,order_details[CustomerID],order_details[Category Name]) -> Confections
B22: CHOPS | C22: 8 | D22: 12348.88 | E22: =_xlfn.XLOOKUP(B22,order_details[CustomerID],order_details[Category Name]) -> Beverages
B23: COMMI | C23: 5 | D23: 3810.75 | E23: =_xlfn.XLOOKUP(B23,order_details[CustomerID],order_details[Category Name]) -> Condiments
B24: CONSH | C24: 3 | D24: 1719.1 | E24: =_xlfn.XLOOKUP(B24,order_details[CustomerID],order_details[Category Name]) -> Beverages
B25: DRACD | C25: 6 | D25: 3763.21 | E25: =_xlfn.XLOOKUP(B25,order_details[CustomerID],order_details[Category Name]) -> Dairy Products
B26: DUMON | C26: 4 | D26: 1615.9 | E26: =_xlfn.XLOOKUP(B26,order_details[CustomerID],order_details[Category Name]) -> Grains/Cereals
B27: EASTC | C27: 8 | D27: 14761.035 | E27: =_xlfn.XLOOKUP(B27,order_details[CustomerID],order_details[Category Name]) -> Dairy Products
B28: ERNSH | C28: 30 | D28: 104874.98 | E28: =_xlfn.XLOOKUP(B28,order_details[CustomerID],order_details[Category Name]) -> Beverages
B29: FAMIA | C29: 7 | D29: 4107.55 | E29: =_xlfn.XLOOKUP(B29,order_details[CustomerID],order_details[Category Name]) -> Confections
B30: FOLIG | C30: 5 | D30: 11666.9 | E30: =_xlfn.XLOOKUP(B30,order_details[CustomerID],order_details[Category Name]) -> Seafood
... B97: WOLZA | C97: 7 | D97: 3531.95 | E97: =_xlfn.XLOOKUP(B97,order_details[CustomerID],order_details[Category Name]) -> Dairy Products
B98: Grand Total | C98: 830 | D98: 1265793

Sheet EDA Q_4
C3: . Which product categories or products contribute most to order revenue? Are there any correlations between orders and customer location or product category?
AB4: Country wise total order count Country and category wise total revenue generation
X7: Country and city wise revenue | AC7: Row Labels | AD7: Count of OrderID | AE7: Row Labels | AF7: Sum of Total_sales
AC8: Argentina | AD8: 16 | AE8: Argentina | AF8: 8119.1
B9: Category name | C9: Sum of Total_sales | Y9: Row Labels | Z9: Sum of Total_sales | AC9: Austria | AD9: 40 | AE9: Beverages | AF9: 1798
B10: Beverages | C10: 267868.18 | Y10: Argentina | Z10: 8119.1 | AC10: Belgium | AD10: 19 | AE10: Condiments | AF10: 907
B11: Condiments | C11: 106047.09 | Y11: Buenos Aires | Z11: 8119.1 | AC11: Brazil | AD11: 83 | AE11: Confections | AF11: 2135.1
B12: Confections | C12: 167357.22 | Y12: Austria | Z12: 128003.84 | AC12: Canada | AD12: 30 | AE12: Dairy Products | AF12: 1143.5
B13: Dairy Products | C13: 234507.29 | Y13: Graz | Z13: 104874.98 | AC13: Denmark | AD13: 18 | AE13: Grains/Cereals | AF13: 390
B14: Grains/Cereals | C14: 95744.588 | Y14: Salzburg | Z14: 23128.86 | AC14: Finland | AD14: 22 | AE14: Produce | AF14: 1139
B15: Meat/Poultry | C15: 163022.36 | Y15: Belgium | Z15: 33824.855 | AC15: France | AD15: 77 | AE15: Seafood | AF15: 606.5
B16: Produce | C16: 99984.58 | Y16: Bruxelles | Z16: 9736.075 | AC16: Germany | AD16: 122 | AE16: Austria | AF16: 128003.84
B17: Seafood | C17: 131261.74 | Y17: Charleroi | Z17: 24088.78 | AC17: Ireland | AD17: 19 | AE17: Beverages | AF17: 23317.3
B18: Grand Total | C18: 1265793 | Y18: Brazil | Z18: 106925.78 | AC18: Italy | AD18: 28 | AE18: Condiments | AF18: 15237.243
Y19: Campinas | Z19: 8414.135 | AC19: Mexico | AD19: 28 | AE19: Confections | AF19: 13534.408
Y20: Resende | Z20: 6068.2 | AC20: Norway | AD20: 6 | AE20: Dairy Products | AF20: 28106.74
B21: Category name | C21: Sum of Total_sales | Y21: Rio de Janeiro | Z21: 51956.98 | AC21: Poland | AD21: 7 | AE21: Grains/Cereals | AF21: 14527.7
B22: Beverages | C22: 1 | Y22: São Paulo | Z22: 40486.462 | AC22: Portugal | AD22: 13 | AE22: Meat/Poultry | AF22: 10821.556
B23: Condiments | C23: 6 | Y23: Canada | Z23: 50196.29 | AC23: Spain | AD23: 23 | AE23: Produce | AF23: 13120.667
B24: Confections | C24: 3 | Y24: Montréal | Z24: 28872.19 | AC24: Sweden | AD24: 37 | AE24: Seafood | AF24: 9338.225
B25: Dairy Products | C25: 2 | Y25: Tsawassen | Z25: 20801.6 | AC25: Switzerland | AD25: 18 | AE25: Belgium | AF25: 33824.855
B26: Grains/Cereals | C26: 8 | Y26: Vancouver | Z26: 522.5 | AC26: UK | AD26: 56 | AE26: Beverages | AF26: 5428.68
B27: Meat/Poultry | C27: 4 | Y27: Denmark | Z27: 32661.022 | AC27: USA | AD27: 122 | AE27: Condiments | AF27: 2454.795
B28: Produce | C28: 7 | Y28: Århus | Z28: 15843.925 | AC28: Venezuela | AD28: 46 | AE28: Confections | AF28: 7479.58
B29: Seafood | C29: 5 | Y29: København | Z29: 16817.097 | AC29: Grand Total | AD29: 830 | AE29: Dairy Products | AF29: 8660
B30: Grand Total | Y30: Finland | Z30: 18810.052 | AE30: Grains/Cereals | AF30: 3226
Y31: Helsinki | Z31: 3161.35 | AE31: Meat/Poultry | AF31: 2138.5
Y32: Oulu | Z32: 15648.702 | AE32: Produce | AF32: 3223.2
Y33: France | Z33: 81358.323 | AE33: Seafood | AF33: 1214.1
Y34: Lille | Z34: 11666.9 | AE34: Brazil | AF34: 106925.78
Y35: Lyon | Z35: 9182.43 | AE35: Beverages | AF35: 37193.445
Y36: Marseille | Z36: 21963.253 | AE36: Condiments | AF36: 11180.76
Y37: Nantes | Z37: 4788.06 | AE37: Confections | AF37: 11436.103
Y38: Paris | Z38: 2423.35 | AE38: Dairy Products | AF38: 15680.45
Y39: Reims | Z39: 1480 | AE39: Grains/Cereals | AF39: 6121.55
Y40: Strasbourg | Z40: 18534.08 | AE40: Meat/Poultry | AF40: 7563.114
Y41: Toulouse | Z41: 9328.2 | AE41: Produce | AF41: 4863.22
Y42: Versailles | Z42: 1992.05 | AE42: Seafood | AF42: 12887.135
... Y101: Grand Total | Z101: 1265793 | AE101: Dairy Products | AF101: 3995.14
AE102: Grains/Cereals | AF102: 1743.5
AE103: Meat/Poultry | AF103: 1056.5
AE104: Produce | AF104: 2186.8
AE105: Seafood | AF105: 1721
AE106: Mexico | AF106: 23582.077
AE107: Beverages | AF107: 7994
AE108: Condiments | AF108: 1235.45
AE109: Confections | AF109: 1897.7275
AE110: Dairy Products | AF110: 4721.9
AE111: Grains/Cereals | AF111: 549.75
AE112: Meat/Poultry | AF112: 2828.9
AE113: Produce | AF113: 2517.75
... AE194: Grand Total | AF194: 1265793

Sheet EDA Q_5
D3: 1. How frequently do different customer segments place orders?
B6: CustomerID | C6: Count of OrderID | D6: Customer segment | G6: Customer segment | H6: Average order per customer | I6: total ordres
B7: ALFKI | C7: 6 | D7: =IF(C7>=10,"Frequent Customers", IF(C7>=4,"Regular Customers", "Occasional Customers")) -> Regular Customers | G7: Frequent Customers | H7: 14.25641 | I7: 556
B8: ANATR | C8: 4 | D8: =IF(C8>=10,"Frequent Customers", IF(C8>=4,"Regular Customers", "Occasional Customers")) -> Regular Customers | G8: Occasional Customers | H8: 2.6 | I8: 26
B9: ANTON | C9: 7 | D9: =IF(C9>=10,"Frequent Customers", IF(C9>=4,"Regular Customers", "Occasional Customers")) -> Regular Customers | G9: Regular Customers | H9: 6.2 | I9: 248
B10: AROUT | C10: 13 | D10: =IF(C10>=10,"Frequent Customers", IF(C10>=4,"Regular Customers", "Occasional Customers")) -> Frequent Customers | G10: Grand Total | H10: 9.3258427 | I10: 830
B11: BERGS | C11: 18 | D11: =IF(C11>=10,"Frequent Customers", IF(C11>=4,"Regular Customers", "Occasional Customers")) -> Frequent Customers
B12: BLAUS | C12: 7 | D12: =IF(C12>=10,"Frequent Customers", IF(C12>=4,"Regular Customers", "Occasional Customers")) -> Regular Customers
B13: BLONP | C13: 11 | D13: =IF(C13>=10,"Frequent Customers", IF(C13>=4,"Regular Customers", "Occasional Customers")) -> Frequent Customers
B14: BOLID | C14: 3 | D14: =IF(C14>=10,"Frequent Customers", IF(C14>=4,"Regular Customers", "Occasional Customers")) -> Occasional Customers
B15: BONAP | C15: 17 | D15: =IF(C15>=10,"Frequent Customers", IF(C15>=4,"Regular Customers", "Occasional Customers")) -> Frequent Customers
B16: BOTTM | C16: 14 | D16: =IF(C16>=10,"Frequent Customers", IF(C16>=4,"Regular Customers", "Occasional Customers")) -> Frequent Customers
B17: BSBEV | C17: 10 | D17: =IF(C17>=10,"Frequent Customers", IF(C17>=4,"Regular Customers", "Occasional Customers")) -> Frequent Customers
B18: CACTU | C18: 6 | D18: =IF(C18>=10,"Frequent Customers", IF(C18>=4,"Regular Customers", "Occasional Customers")) -> Regular Customers
B19: CENTC | C19: 1 | D19: =IF(C19>=10,"Frequent Customers", IF(C19>=4,"Regular Customers", "Occasional Customers")) -> Occasional Customers
B20: CHOPS | C20: 8 | D20: =IF(C20>=10,"Frequent Customers", IF(C20>=4,"Regular Customers", "Occasional Customers")) -> Regular Customers
B21: COMMI | C21: 5 | D21: =IF(C21>=10,"Frequent Customers", IF(C21>=4,"Regular Customers", "Occasional Customers")) -> Regular Customers
B22: CONSH | C22: 3 | D22: =IF(C22>=10,"Frequent Customers", IF(C22>=4,"Regular Customers", "Occasional Customers")) -> Occasional Customers
... B95: WOLZA | C95: 7 | D95: =IF(C95>=10,"Frequent Customers", IF(C95>=4,"Regular Customers", "Occasional Customers")) -> Regular Customers
B96: Grand Total | C96: 830

Sheet EDA Q_6
C4: 1. What is the geographic and title-wise distribution of employees?
D11: Title | E11: Count of EmployeeID | G11: Count of EmployeeID | H11: Country
D12: Inside Sales Coordinator | E12: 1 | G12: Title | H12: UK | I12: USA | J12: Grand Total
D13: Sales Manager | E13: 1 | G13: Inside Sales Coordinator | I13: 1 | J13: 1
D14: Sales Representative | E14: 6 | G14: Sales Manager | H14: 1 | J14: 1
D15: Vice President, Sales | E15: 1 | G15: Sales Representative | H15: 3 | I15: 3 | J15: 6
D16: Grand Total | E16: 9 | G16: Vice President, Sales | I16: 1 | J16: 1
G17: Grand Total | H17: 4 | I17: 5 | J17: 9
D19: Country | E19: Count of EmployeeID
D20: UK | E20: 4
D21: USA | E21: 5
D22: Grand Total | E22: 9

Sheet EDA Q_7
G4: What trends can we observe in hire dates across employee titles?
Q8: Average Hire Date by Employee Title | Y8: Earliest and Latest Hire Date per Title
D10: Count of EmployeeID | E10: Title | L10: Title | M10: Average of Hire year
D11: Hire year | E11: Inside Sales Coordinator | F11: Sales Manager | G11: Sales Representative | H11: Vice President, Sales | I11: Grand Total | L11: Inside Sales Coordinator | M11: 1994
D12: 1992 | G12: 2 | H12: 1 | I12: 3 | L12: Sales Manager | M12: 1993
D13: 1993 | F13: 1 | G13: 2 | I13: 3 | L13: Sales Representative | M13: 1993
D14: 1994 | E14: 1 | G14: 2 | I14: 3 | L14: Vice President, Sales | M14: 1992
D15: Grand Total | E15: 1 | F15: 1 | G15: 6 | H15: 1 | I15: 9 | L15: Grand Total | M15: 1993
Q26: Employees Hired per Year by Title

Sheet EDA Q_8
C4: 1. What patterns exist in employee title and courtesy title distributions?
C10: title | D10: Count of EmployeeID
C11: Inside Sales Coordinator | D11: 1
C12: Ms. | D12: 1
C13: Sales Manager | D13: 1
C14: Mr. | D14: 1
C15: Sales Representative | D15: 6
C16: Mr. | D16: 2
C17: Mrs. | D17: 1
C18: Ms. | D18: 3
C19: Vice President, Sales | D19: 1
C20: Dr. | D20: 1
C21: Grand Total | D21: 9

Sheet EDA Q_9
A1: Are there correlations between product pricing, stock levels, and sales performance?
M3: Stock Levels vs Quantity Sold | S3: Unit Price vs Quantity Sold
B5: ProductID | C5: Quantity sold | D5: Unit price | E5: Units in stock | F5: Total Revenue
B6: 1 | C6: =SUMIFS(order_details[Quantity],order_details[ProductID],'EDA Q_9'!B6) -> 828 | D6: =_xlfn.XLOOKUP(B6,products[ProductID],products[UnitPrice]) -> 18 | E6: =_xlfn.XLOOKUP(B6,products[ProductID],products[UnitsInStock]) -> 39 | F6: =D6*C6 -> 14904 | H6: Price vs Sales Performance
B7: 2 | C7: =SUMIFS(order_details[Quantity],order_details[ProductID],'EDA Q_9'!B7) -> 1057 | D7: =_xlfn.XLOOKUP(B7,products[ProductID],products[UnitPrice]) -> 19 | E7: =_xlfn.XLOOKUP(B7,products[ProductID],products[UnitsInStock]) -> 17 | F7: =D7*C7 -> 20083 | H7: =CORREL(D6:D82,C6:C82) -> -0.03778077
B8: 3 | C8: =SUMIFS(order_details[Quantity],order_details[ProductID],'EDA Q_9'!B8) -> 328 | D8: =_xlfn.XLOOKUP(B8,products[ProductID],products[UnitPrice]) -> 10 | E8: =_xlfn.XLOOKUP(B8,products[ProductID],products[UnitsInStock]) -> 13 | F8: =D8*C8 -> 3280
B9: 4 | C9: =SUMIFS(order_details[Quantity],order_details[ProductID],'EDA Q_9'!B9) -> 453 | D9: =_xlfn.XLOOKUP(B9,products[ProductID],products[UnitPrice]) -> 22 | E9: =_xlfn.XLOOKUP(B9,products[ProductID],products[UnitsInStock]) -> 53 | F9: =D9*C9 -> 9966
B10: 5 | C10: =SUMIFS(order_details[Quantity],order_details[ProductID],'EDA Q_9'!B10) -> 298 | D10: =_xlfn.XLOOKUP(B10,products[ProductID],products[UnitPrice]) -> 21.35 | E10: =_xlfn.XLOOKUP(B10,products[ProductID],products[UnitsInStock]) -> 0 | F10: =D10*C10 -> 6362.3
B11: 6 | C11: =SUMIFS(order_details[Quantity],order_details[ProductID],'EDA Q_9'!B11) -> 301 | D11: =_xlfn.XLOOKUP(B11,products[ProductID],products[UnitPrice]) -> 25 | E11: =_xlfn.XLOOKUP(B11,products[ProductID],products[UnitsInStock]) -> 120 | F11: =D11*C11 -> 7525
B12: 7 | C12: =SUMIFS(order_details[Quantity],order_details[ProductID],'EDA Q_9'!B12) -> 763 | D12: =_xlfn.XLOOKUP(B12,products[ProductID],products[UnitPrice]) -> 30 | E12: =_xlfn.XLOOKUP(B12,products[ProductID],products[UnitsInStock]) -> 15 | F12: =D12*C12 -> 22890 | H12: Stock Level vs Sales Performance
B13: 8 | C13: =SUMIFS(order_details[Quantity],order_details[ProductID],'EDA Q_9'!B13) -> 372 | D13: =_xlfn.XLOOKUP(B13,products[ProductID],products[UnitPrice]) -> 40 | E13: =_xlfn.XLOOKUP(B13,products[ProductID],products[UnitsInStock]) -> 6 | F13: =D13*C13 -> 14880 | H13: =CORREL(E6:E82,C6:C82) -> -0.013413787
B14: 9 | C14: =SUMIFS(order_details[Quantity],order_details[ProductID],'EDA Q_9'!B14) -> 95 | D14: =_xlfn.XLOOKUP(B14,products[ProductID],products[UnitPrice]) -> 97 | E14: =_xlfn.XLOOKUP(B14,products[ProductID],products[UnitsInStock]) -> 29 | F14: =D14*C14 -> 9215
B15: 10 | C15: =SUMIFS(order_details[Quantity],order_details[ProductID],'EDA Q_9'!B15) -> 742 | D15: =_xlfn.XLOOKUP(B15,products[ProductID],products[UnitPrice]) -> 31 | E15: =_xlfn.XLOOKUP(B15,products[ProductID],products[UnitsInStock]) -> 31 | F15: =D15*C15 -> 23002
B16: 11 | C16: =SUMIFS(order_details[Quantity],order_details[ProductID],'EDA Q_9'!B16) -> 706 | D16: =_xlfn.XLOOKUP(B16,products[ProductID],products[UnitPrice]) -> 21 | E16: =_xlfn.XLOOKUP(B16,products[ProductID],products[UnitsInStock]) -> 22 | F16: =D16*C16 -> 14826
B17: 12 | C17: =SUMIFS(order_details[Quantity],order_details[ProductID],'EDA Q_9'!B17) -> 344 | D17: =_xlfn.XLOOKUP(B17,products[ProductID],products[UnitPrice]) -> 38 | E17: =_xlfn.XLOOKUP(B17,products[ProductID],products[UnitsInStock]) -> 86 | F17: =D17*C17 -> 13072 | H17: Price vs Stock Level
B18: 13 | C18: =SUMIFS(order_details[Quantity],order_details[ProductID],'EDA Q_9'!B18) -> 891 | D18: =_xlfn.XLOOKUP(B18,products[ProductID],products[UnitPrice]) -> 6 | E18: =_xlfn.XLOOKUP(B18,products[ProductID],products[UnitsInStock]) -> 24 | F18: =D18*C18 -> 5346 | H18: =CORREL(D6:D82,E6:E82) -> -0.17205534
B19: 14 | C19: =SUMIFS(order_details[Quantity],order_details[ProductID],'EDA Q_9'!B19) -> 404 | D19: =_xlfn.XLOOKUP(B19,products[ProductID],products[UnitPrice]) -> 23.25 | E19: =_xlfn.XLOOKUP(B19,products[ProductID],products[UnitsInStock]) -> 35 | F19: =D19*C19 -> 9393
B20: 15 | C20: =SUMIFS(order_details[Quantity],order_details[ProductID],'EDA Q_9'!B20) -> 122 | D20: =_xlfn.XLOOKUP(B20,products[ProductID],products[UnitPrice]) -> 15.5 | E20: =_xlfn.XLOOKUP(B20,products[ProductID],products[UnitsInStock]) -> 39 | F20: =D20*C20 -> 1891
B21: 16 | C21: =SUMIFS(order_details[Quantity],order_details[ProductID],'EDA Q_9'!B21) -> 1158 | D21: =_xlfn.XLOOKUP(B21,products[ProductID],products[UnitPrice]) -> 17.45 | E21: =_xlfn.XLOOKUP(B21,products[ProductID],products[UnitsInStock]) -> 29 | F21: =D21*C21 -> 20207.1
B22: 17 | C22: =SUMIFS(order_details[Quantity],order_details[ProductID],'EDA Q_9'!B22) -> 978 | D22: =_xlfn.XLOOKUP(B22,products[ProductID],products[UnitPrice]) -> 39 | E22: =_xlfn.XLOOKUP(B22,products[ProductID],products[UnitsInStock]) -> 0 | F22: =D22*C22 -> 38142
B23: 18 | C23: =SUMIFS(order_details[Quantity],order_details[ProductID],'EDA Q_9'!B23) -> 539 | D23: =_xlfn.XLOOKUP(B23,products[ProductID],products[UnitPrice]) -> 62.5 | E23: =_xlfn.XLOOKUP(B23,products[ProductID],products[UnitsInStock]) -> 42 | F23: =D23*C23 -> 33687.5
B24: 19 | C24: =SUMIFS(order_details[Quantity],order_details[ProductID],'EDA Q_9'!B24) -> 723 | D24: =_xlfn.XLOOKUP(B24,products[ProductID],products[UnitPrice]) -> 9.2 | E24: =_xlfn.XLOOKUP(B24,products[ProductID],products[UnitsInStock]) -> 25 | F24: =D24*C24 -> 6651.6
B25: 20 | C25: =SUMIFS(order_details[Quantity],order_details[ProductID],'EDA Q_9'!B25) -> 313 | D25: =_xlfn.XLOOKUP(B25,products[ProductID],products[UnitPrice]) -> 81 | E25: =_xlfn.XLOOKUP(B25,products[ProductID],products[UnitsInStock]) -> 40 | F25: =D25*C25 -> 25353
B26: 21 | C26: =SUMIFS(order_details[Quantity],order_details[ProductID],'EDA Q_9'!B26) -> 1016 | D26: =_xlfn.XLOOKUP(B26,products[ProductID],products[UnitPrice]) -> 10 | E26: =_xlfn.XLOOKUP(B26,products[ProductID],products[UnitsInStock]) -> 3 | F26: =D26*C26 -> 10160
B27: 22 | C27: =SUMIFS(order_details[Quantity],order_details[ProductID],'EDA Q_9'!B27) -> 348 | D27: =_xlfn.XLOOKUP(B27,products[ProductID],products[UnitPrice]) -> 21 | E27: =_xlfn.XLOOKUP(B27,products[ProductID],products[UnitsInStock]) -> 104 | F27: =D27*C27 -> 7308
B28: 23 | C28: =SUMIFS(order_details[Quantity],order_details[ProductID],'EDA Q_9'!B28) -> 580 | D28: =_xlfn.XLOOKUP(B28,products[ProductID],products[UnitPrice]) -> 9 | E28: =_xlfn.XLOOKUP(B28,products[ProductID],products[UnitsInStock]) -> 61 | F28: =D28*C28 -> 5220
B29: 24 | C29: =SUMIFS(order_details[Quantity],order_details[ProductID],'EDA Q_9'!B29) -> 1125 | D29: =_xlfn.XLOOKUP(B29,products[ProductID],products[UnitPrice]) -> 4.5 | E29: =_xlfn.XLOOKUP(B29,products[ProductID],products[UnitsInStock]) -> 20 | F29: =D29*C29 -> 5062.5
B30: 25 | C30: =SUMIFS(order_details[Quantity],order_details[ProductID],'EDA Q_9'!B30) -> 318 | D30: =_xlfn.XLOOKUP(B30,products[ProductID],products[UnitPrice]) -> 14 | E30: =_xlfn.XLOOKUP(B30,products[ProductID],products[UnitsInStock]) -> 76 | F30: =D30*C30 -> 4452
... B82: 77 | C82: =SUMIFS(order_details[Quantity],order_details[ProductID],'EDA Q_9'!B82) -> 791 | D82: =_xlfn.XLOOKUP(B82,products[ProductID],products[UnitPrice]) -> 13 | E82: =_xlfn.XLOOKUP(B82,products[ProductID],products[UnitsInStock]) -> 32 | F82: =D82*C82 -> 10283
B83: Grand Total

Sheet EDA Q_10
C3: How does product demand change over months or seasons?
B7: Row Labels | C7: Sum of Quantity | D7: Sum of Total_sales | G7: Year / Month | H7: Sum of Quantity
B8: 1994 | C8: 7381 | D8: 162844.34 | G8: 1994 | H8: 7381
B9: Aug | C9: 1462 | D9: 27861.895 | G9: Aug | H9: 1462
B10: Sep | C10: 1322 | D10: 25485.275 | G10: Sep | H10: 1322
B11: Oct | C11: 1124 | D11: 26381.4 | G11: Oct | H11: 1124
B12: Nov | C12: 1669 | D12: 35931.725 | G12: Nov | H12: 1669
B13: Dec | C13: 1804 | D13: 47184.045 | G13: Dec | H13: 1804
B14: 1995 | C14: 25007 | D14: 590926.4 | G14: 1995 | H14: 25007
B15: Jan | C15: 2200 | D15: 45239.63 | G15: Jan | H15: 2200
B16: Feb | C16: 1951 | D16: 52540.245 | G16: Feb | H16: 1951
B17: Mar | C17: 2582 | D17: 47201.46 | G17: Mar | H17: 2582
B18: Apr | C18: 1622 | D18: 35124.515 | G18: Apr | H18: 1622
B19: May | C19: 2060 | D19: 56455.657 | G19: May | H19: 2060
B20: Jun | C20: 2164 | D20: 53781.29 | G20: Jun | H20: 2164
B21: Jul | C21: 1635 | D21: 36362.803 | G21: Jul | H21: 1635
B22: Aug | C22: 2054 | D22: 51020.857 | G22: Aug | H22: 2054
B23: Sep | C23: 1861 | D23: 47287.67 | G23: Sep | H23: 1861
B24: Oct | C24: 2343 | D24: 55629.242 | G24: Oct | H24: 2343
B25: Nov | C25: 2657 | D25: 66461.426 | G25: Nov | H25: 2657
B26: Dec | C26: 1878 | D26: 43821.609 | G26: Dec | H26: 1878
B27: 1996 | C27: 18929 | D27: 512022.29 | G27: 1996 | H27: 18929
B28: Jan | C28: 2682 | D28: 71398.428 | G28: Jan | H28: 2682
B29: Feb | C29: 3293 | D29: 90117.711 | G29: Feb | H29: 3293
B30: Mar | C30: 3288 | D30: 103519.69 | G30: Mar | H30: 3288
B31: Apr | C31: 4065 | D31: 104854.16 | G31: Apr | H31: 4065
B32: May | C32: 4957 | D32: 129247.25 | G32: May | H32: 4957
B33: Jun | C33: 644 | D33: 12885.06 | G33: Jun | H33: 644
B34: Grand Total | C34: 51317 | D34: 1265793

Sheet EDA Q_12
D3: Are there any regional trends in supplier distribution and pricing?
B7: Supplier country | C7: No of suppliers | D7: Average of UnitPrice | E7: Max of UnitPrice | F7: Min of UnitPrice | H7: Supplier country | I7: Average of UnitPrice | S7: Supplier country | T7: No of suppliers
B8: Australia | C8: 8 | D8: 33.83125 | E8: 62.5 | F8: 7 | H8: Australia | I8: 33.83125 | S8: Australia | T8: 8
B9: Brazil | C9: 1 | D9: 4.5 | E9: 4.5 | F9: 4.5 | H9: Brazil | I9: 4.5 | S9: Brazil | T9: 1
B10: Canada | C10: 4 | D10: 27.3125 | E10: 49.3 | F10: 7.45 | H10: Canada | I10: 27.3125 | S10: Canada | T10: 4
B11: Denmark | C11: 2 | D11: 10.75 | E11: 12 | F11: 9.5 | H11: Denmark | I11: 10.75 | S11: Denmark | T11: 2
B12: Finland | C12: 3 | D12: 18.083333 | E12: 20 | F12: 16.25 | H12: Finland | I12: 18.083333 | S12: Finland | T12: 3
B13: France | C13: 5 | D13: 76.75 | E13: 263.5 | F13: 13.25 | H13: France | I13: 76.75 | S13: France | T13: 5
B14: Germany | C14: 9 | D14: 37.601111 | E14: 123.79 | F14: 7.75 | H14: Germany | I14: 37.601111 | S14: Germany | T14: 9
B15: Italy | C15: 5 | D15: 27.36 | E15: 38 | F15: 12.5 | H15: Italy | I15: 27.36 | S15: Italy | T15: 5
B16: Japan | C16: 6 | D16: 30.458333 | E16: 97 | F16: 6 | H16: Japan | I16: 30.458333 | S16: Japan | T16: 6
B17: Netherlands | C17: 2 | D17: 11.125 | E17: 12.75 | F17: 9.5 | H17: Netherlands | I17: 11.125 | S17: Netherlands | T17: 2
B18: Norway | C18: 3 | D18: 20 | E18: 36 | F18: 2.5 | H18: Norway | I18: 20 | S18: Norway | T18: 3
B19: Singapore | C19: 3 | D19: 26.483333 | E19: 46 | F19: 14 | H19: Singapore | I19: 26.483333 | S19: Singapore | T19: 3
... B24: USA | C24: 12 | D24: 20.870833 | E24: 40 | F24: 9.65 | H24: USA | I24: 20.870833 | S24: USA | T24: 12
B25: Grand Total | C25: 77 | D25: 28.866364 | E25: 263.5 | F25: 2.5 | H25: Grand Total | I25: 28.866364

Sheet EDA Q_13
D3: How are suppliers distributed across different product categories?
C5: ProductID | D5: SupplierID | E5: CategoryID | F5: Company name | G5: Category name
C6: 1 | D6: 1 | E6: 1 | F6: =_xlfn.XLOOKUP(D6,suppliers[SupplierID],suppliers[CompanyName]) -> Exotic Liquids | G6: =_xlfn.XLOOKUP(E6,categories[CategoryID],categories[CategoryName]) -> Beverages | I6: Category name | J6: Count of SupplierID
C7: 2 | D7: 1 | E7: 1 | F7: =_xlfn.XLOOKUP(D7,suppliers[SupplierID],suppliers[CompanyName]) -> Exotic Liquids | G7: =_xlfn.XLOOKUP(E7,categories[CategoryID],categories[CategoryName]) -> Beverages | I7: Beverages | J7: 12
C8: 3 | D8: 1 | E8: 2 | F8: =_xlfn.XLOOKUP(D8,suppliers[SupplierID],suppliers[CompanyName]) -> Exotic Liquids | G8: =_xlfn.XLOOKUP(E8,categories[CategoryID],categories[CategoryName]) -> Condiments | I8: Condiments | J8: 12
C9: 4 | D9: 2 | E9: 2 | F9: =_xlfn.XLOOKUP(D9,suppliers[SupplierID],suppliers[CompanyName]) -> New Orleans Cajun Delights | G9: =_xlfn.XLOOKUP(E9,categories[CategoryID],categories[CategoryName]) -> Condiments | I9: Confections | J9: 13
C10: 5 | D10: 2 | E10: 2 | F10: =_xlfn.XLOOKUP(D10,suppliers[SupplierID],suppliers[CompanyName]) -> New Orleans Cajun Delights | G10: =_xlfn.XLOOKUP(E10,categories[CategoryID],categories[CategoryName]) -> Condiments | I10: Dairy Products | J10: 10
C11: 6 | D11: 3 | E11: 2 | F11: =_xlfn.XLOOKUP(D11,suppliers[SupplierID],suppliers[CompanyName]) -> Grandma Kelly's Homestead | G11: =_xlfn.XLOOKUP(E11,categories[CategoryID],categories[CategoryName]) -> Condiments | I11: Grains/Cereals | J11: 7
C12: 7 | D12: 3 | E12: 7 | F12: =_xlfn.XLOOKUP(D12,suppliers[SupplierID],suppliers[CompanyName]) -> Grandma Kelly's Homestead | G12: =_xlfn.XLOOKUP(E12,categories[CategoryID],categories[CategoryName]) -> Produce | I12: Meat/Poultry | J12: 6
C13: 8 | D13: 3 | E13: 2 | F13: =_xlfn.XLOOKUP(D13,suppliers[SupplierID],suppliers[CompanyName]) -> Grandma Kelly's Homestead | G13: =_xlfn.XLOOKUP(E13,categories[CategoryID],categories[CategoryName]) -> Condiments | I13: Produce | J13: 5
C14: 9 | D14: 4 | E14: 6 | F14: =_xlfn.XLOOKUP(D14,suppliers[SupplierID],suppliers[CompanyName]) -> Tokyo Traders | G14: =_xlfn.XLOOKUP(E14,categories[CategoryID],categories[CategoryName]) -> Meat/Poultry | I14: Seafood | J14: 12
C15: 10 | D15: 4 | E15: 8 | F15: =_xlfn.XLOOKUP(D15,suppliers[SupplierID],suppliers[CompanyName]) -> Tokyo Traders | G15: =_xlfn.XLOOKUP(E15,categories[CategoryID],categories[CategoryName]) -> Seafood | I15: Grand Total | J15: 77
C16: 11 | D16: 5 | E16: 4 | F16: =_xlfn.XLOOKUP(D16,suppliers[SupplierID],suppliers[CompanyName]) -> Cooperativa de Quesos 'Las Cabras' | G16: =_xlfn.XLOOKUP(E16,categories[CategoryID],categories[CategoryName]) -> Dairy Products
C17: 12 | D17: 5 | E17: 4 | F17: =_xlfn.XLOOKUP(D17,suppliers[SupplierID],suppliers[CompanyName]) -> Cooperativa de Quesos 'Las Cabras' | G17: =_xlfn.XLOOKUP(E17,categories[CategoryID],categories[CategoryName]) -> Dairy Products
C18: 13 | D18: 6 | E18: 8 | F18: =_xlfn.XLOOKUP(D18,suppliers[SupplierID],suppliers[CompanyName]) -> Mayumi's | G18: =_xlfn.XLOOKUP(E18,categories[CategoryID],categories[CategoryName]) -> Seafood
C19: 14 | D19: 6 | E19: 7 | F19: =_xlfn.XLOOKUP(D19,suppliers[SupplierID],suppliers[CompanyName]) -> Mayumi's | G19: =_xlfn.XLOOKUP(E19,categories[CategoryID],categories[CategoryName]) -> Produce
C20: 15 | D20: 6 | E20: 2 | F20: =_xlfn.XLOOKUP(D20,suppliers[SupplierID],suppliers[CompanyName]) -> Mayumi's | G20: =_xlfn.XLOOKUP(E20,categories[CategoryID],categories[CategoryName]) -> Condiments
C21: 16 | D21: 7 | E21: 3 | F21: =_xlfn.XLOOKUP(D21,suppliers[SupplierID],suppliers[CompanyName]) -> Pavlova, Ltd. | G21: =_xlfn.XLOOKUP(E21,categories[CategoryID],categories[CategoryName]) -> Confections
C22: 17 | D22: 7 | E22: 6 | F22: =_xlfn.XLOOKUP(D22,suppliers[SupplierID],suppliers[CompanyName]) -> Pavlova, Ltd. | G22: =_xlfn.XLOOKUP(E22,categories[CategoryID],categories[CategoryName]) -> Meat/Poultry
C23: 18 | D23: 7 | E23: 8 | F23: =_xlfn.XLOOKUP(D23,suppliers[SupplierID],suppliers[CompanyName]) -> Pavlova, Ltd. | G23: =_xlfn.XLOOKUP(E23,categories[CategoryID],categories[CategoryName]) -> Seafood
C24: 19 | D24: 8 | E24: 3 | F24: =_xlfn.XLOOKUP(D24,suppliers[SupplierID],suppliers[CompanyName]) -> Specialty Biscuits, Ltd. | G24: =_xlfn.XLOOKUP(E24,categories[CategoryID],categories[CategoryName]) -> Confections
C25: 20 | D25: 8 | E25: 3 | F25: =_xlfn.XLOOKUP(D25,suppliers[SupplierID],suppliers[CompanyName]) -> Specialty Biscuits, Ltd. | G25: =_xlfn.XLOOKUP(E25,categories[CategoryID],categories[CategoryName]) -> Confections
C26: 21 | D26: 8 | E26: 3 | F26: =_xlfn.XLOOKUP(D26,suppliers[SupplierID],suppliers[CompanyName]) -> Specialty Biscuits, Ltd. | G26: =_xlfn.XLOOKUP(E26,categories[CategoryID],categories[CategoryName]) -> Confections
C27: 22 | D27: 9 | E27: 5 | F27: =_xlfn.XLOOKUP(D27,suppliers[SupplierID],suppliers[CompanyName]) -> PB Knäckebröd AB | G27: =_xlfn.XLOOKUP(E27,categories[CategoryID],categories[CategoryName]) -> Grains/Cereals
... C82: 77 | D82: 12 | E82: 2 | F82: =_xlfn.XLOOKUP(D82,suppliers[SupplierID],suppliers[CompanyName]) -> Plutzer Lebensmittelgroßmärkte AG | G82: =_xlfn.XLOOKUP(E82,categories[CategoryID],categories[CategoryName]) -> Condiments

Sheet EDA Q_14
B3: How do supplier pricing and categories relate across different regions?
B7: Supplier country | C7: Average of UnitPrice | D7: Count of ProductID | F7: Average of UnitPrice | G7: Column Labels
B8: Australia | C8: 33.83125 | D8: 8 | F8: Supplier country | G8: Beverages | H8: Condiments | I8: Confections | J8: Dairy Products | K8: Grains/Cereals | L8: Meat/Poultry | M8: Produce | N8: Seafood | O8: Grand Total
B9: Beverages | C9: 15 | D9: 1 | F9: Australia | G9: 15 | H9: 43.9 | I9: 17.45 | K9: 7 | L9: 35.9 | M9: 53 | N9: 62.5 | O9: 33.83125
B10: Condiments | C10: 43.9 | D10: 1 | F10: Brazil | G10: 4.5 | O10: 4.5
B11: Confections | C11: 17.45 | D11: 1 | F11: Canada | H11: 28.5 | I11: 49.3 | L11: 15.725 | O11: 27.3125
B12: Grains/Cereals | C12: 7 | D12: 1 | F12: Denmark | N12: 10.75 | O12: 10.75
B13: Meat/Poultry | C13: 35.9 | D13: 2 | F13: Finland | G13: 18 | I13: 18.125 | O13: 18.083333
B14: Produce | C14: 53 | D14: 1 | F14: France | G14: 140.75 | J14: 44.5 | N14: 13.25 | O14: 76.75
B15: Seafood | C15: 62.5 | D15: 1 | F15: Germany | G15: 7.75 | H15: 13 | I15: 29.71 | K15: 33.25 | L15: 123.79 | M15: 45.6 | N15: 25.89 | O15: 37.601111
B16: Brazil | C16: 4.5 | D16: 1 | F16: Italy | J16: 26.433333 | K16: 28.75 | O16: 27.36
B17: Beverages | C17: 4.5 | D17: 1 | F17: Japan | H17: 15.5 | L17: 97 | M17: 16.625 | N17: 18.5 | O17: 30.458333
B18: Canada | C18: 27.3125 | D18: 4 | F18: Netherlands | I18: 11.125 | O18: 11.125
B19: Condiments | C19: 28.5 | D19: 1 | F19: Norway | J19: 20 | O19: 20
B20: Confections | C20: 49.3 | D20: 1 | F20: Singapore | G20: 46 | H20: 19.45 | K20: 14 | O20: 26.483333
B21: Meat/Poultry | C21: 15.725 | D21: 2 | F21: Spain | J21: 29.5 | O21: 29.5
B22: Denmark | C22: 10.75 | D22: 2 | F22: Sweden | N22: 20 | O22: 20
B23: Seafood | C23: 10.75 | D23: 2 | F23: Sweden | K23: 15 | O23: 15
B24: Finland | C24: 18.083333 | D24: 3 | F24: UK | G24: 18.5 | H24: 10 | I24: 28.175 | O24: 22.814286
B25: Beverages | C25: 18 | D25: 1 | F25: USA | G25: 15.333333 | H25: 24.4 | M25: 30 | N25: 14.025 | O25: 20.870833
B26: Confections | C26: 18.125 | D26: 2 | F26: Grand Total | G26: 37.979167 | H26: 23.0625 | I26: 25.16 | J26: 28.73 | K26: 20.25 | L26: 54.006667 | M26: 32.37 | N26: 20.6825 | O26: 28.866364
B27: France | C27: 76.75 | D27: 5
B28: Beverages | C28: 140.75 | D28: 2
B29: Dairy Products | C29: 44.5 | D29: 2
B30: Seafood | C30: 13.25 | D30: 1
B31: Germany | C31: 37.601111 | D31: 9
B32: Beverages | C32: 7.75 | D32: 1
B33: Condiments | C33: 13 | D33: 1
B34: Confections | C34: 29.71 | D34: 3
B35: Grains/Cereals | C35: 33.25 | D35: 1
B36: Meat/Poultry | C36: 123.79 | D36: 1
B37: Produce | C37: 45.6 | D37: 1
B38: Seafood | C38: 25.89 | D38: 1
... B70: Grand Total | C70: 28.866364 | D70: 77

Sheet categories
A1: CategoryID | B1: CategoryName | C1: Description
A2: 1 | B2: Beverages | C2: Soft drinks, coffees, teas, beers, and ales
A3: 2 | B3: Condiments | C3: Sweet and savory sauces, relishes, spreads, and seasonings
A4: 3 | B4: Confections | C4: Desserts, candies, and sweet breads
A5: 4 | B5: Dairy Products | C5: Cheeses
A6: 5 | B6: Grains/Cereals | C6: Breads, crackers, pasta, and cereal
A7: 6 | B7: Meat/Poultry | C7: Prepared meats
A8: 7 | B8: Produce | C8: Dried fruit and bean curd
A9: 8 | B9: Seafood | C9: Seaweed and fish

Sheet customers
A1: Column1 | B1: Column2 | C1: Column3 | D1: Column4 | E1: Column5 | F1: Column6 | G1: Column7 | H1: Column8 | I1: Column9 | J1: Column10
A2: CustomerID | B2: CompanyName | C2: ContactName | D2: ContactTitle | E2: Address | F2: City | G2: Region | H2: PostalCode | I2: Country | J2: Phone
A3: ALFKI | B3: Alfreds Futterkiste | C3: Maria Anders | D3: Sales Representative | E3: Obere Str. 57 | F3: Berlin | H3: 12209 | I3: Germany | J3: 030-0074321
A4: ANATR | B4: Ana Trujillo Emparedados y helados | C4: Ana Trujillo | D4: Owner | E4: Avda. de la Constitución 2222 | F4: México D.F. | H4: 05021 | I4: Mexico | J4: (5) 555-4729
A5: ANTON | B5: Antonio Moreno Taquería | C5: Antonio Moreno | D5: Owner | E5: Mataderos 2312 | F5: México D.F. | H5: 05023 | I5: Mexico | J5: (5) 555-3932
A6: AROUT | B6: Around the Horn | C6: Thomas Hardy | D6: Sales Representative | E6: 120 Hanover Sq. | F6: London | H6: WA1 1DP | I6: UK | J6: (171) 555-7788
A7: BERGS | B7: Berglunds snabbköp | C7: Christina Berglund | D7: Order Administrator | E7: Berguvsvägen 8 | F7: Luleå | H7: S-958 22 | I7: Sweden | J7: 0921-12 34 65
A8: BLAUS | B8: Blauer See Delikatessen | C8: Hanna Moos | D8: Sales Representative | E8: Forsterstr. 57 | F8: Mannheim | H8: 68306 | I8: Germany | J8: 0621-08460
A9: BLONP | B9: Blondel père et fils | C9: Frédérique Citeaux | D9: Marketing Manager | E9: 24, place Kléber | F9: Strasbourg | H9: 67000 | I9: France | J9: 88.60.15.31
A10: BOLID | B10: Bólido Comidas preparadas | C10: Martín Sommer | D10: Owner | E10: C/ Araquil, 67 | F10: Madrid | H10: 28023 | I10: Spain | J10: (91) 555 22 82
A11: BONAP | B11: Bon app' | C11: Laurence Lebihan | D11: Owner | E11: 12, rue des Bouchers | F11: Marseille | H11: 13008 | I11: France | J11: 91.24.45.40
A12: BOTTM | B12: Bottom-Dollar Markets | C12: Elizabeth Lincoln | D12: Accounting Manager | E12: 23 Tsawassen Blvd. | F12: Tsawassen | G12: BC | H12: T2F 8M4 | I12: Canada | J12: (604) 555-4729
A13: BSBEV | B13: B's Beverages | C13: Victoria Ashworth | D13: Sales Representative | E13: Fauntleroy Circus | F13: London | H13: EC2 5NT | I13: UK | J13: (171) 555-1212
A14: CACTU | B14: Cactus Comidas para llevar | C14: Patricio Simpson | D14: Sales Agent | E14: Cerrito 333 | F14: Buenos Aires | H14: 1010 | I14: Argentina | J14: (1) 135-5555
A15: CENTC | B15: Centro comercial Moctezuma | C15: Francisco Chang | D15: Marketing Manager | E15: Sierras de Granada 9993 | F15: México D.F. | H15: 05022 | I15: Mexico | J15: (5) 555-3392
A16: CHOPS | B16: Chop-suey Chinese | C16: Yang Wang | D16: Owner | E16: Hauptstr. 29 | F16: Bern | H16: 3012 | I16: Switzerland | J16: 0452-076545
A17: COMMI | B17: Comércio Mineiro | C17: Pedro Afonso | D17: Sales Associate | E17: Av. dos Lusíadas, 23 | F17: São Paulo | G17: SP | H17: 05432-043 | I17: Brazil | J17: (11) 555-7647
A18: CONSH | B18: Consolidated Holdings | C18: Elizabeth Brown | D18: Sales Representative | E18: Berkeley Gardens 12 Brewery | F18: London | H18: WX1 6LT | I18: UK | J18: (171) 555-2282
A19: DRACD | B19: Drachenblut Delikatessen | C19: Sven Ottlieb | D19: Order Administrator | E19: Walserweg 21 | F19: Aachen | H19: 52066 | I19: Germany | J19: 0241-039123
A20: DUMON | B20: Du monde entier | C20: Janine Labrune | D20: Owner | E20: 67, rue des Cinquante Otages | F20: Nantes | H20: 44000 | I20: France | J20: 40.67.88.88
A21: EASTC | B21: Eastern Connection | C21: Ann Devon | D21: Sales Agent | E21: 35 King George | F21: London | H21: WX3 6FW | I21: UK | J21: (171) 555-0297
A22: ERNSH | B22: Ernst Handel | C22: Roland Mendel | D22: Sales Manager | E22: Kirchgasse 6 | F22: Graz | H22: 8010 | I22: Austria | J22: 7675-3425
A23: FAMIA | B23: Familia Arquibaldo | C23: Aria Cruz | D23: Marketing Assistant | E23: Rua Orós, 92 | F23: São Paulo | G23: SP | H23: 05442-030 | I23: Brazil | J23: (11) 555-9857
A24: FISSA | B24: FISSA Fabrica Inter. Salchichas S.A. | C24: Diego Roel | D24: Accounting Manager | E24: C/ Moralzarzal, 86 | F24: Madrid | H24: 28034 | I24: Spain | J24: (91) 555 94 44
A25: FOLIG | B25: Folies gourmandes | C25: Martine Rancé | D25: Assistant Sales Agent | E25: 184, chaussée de Tournai | F25: Lille | H25: 59000 | I25: France | J25: 20.16.10.16
A26: FOLKO | B26: Folk och fä HB | C26: Maria Larsson | D26: Owner | E26: Åkergatan 24 | F26: Bräcke | H26: S-844 67 | I26: Sweden | J26: 0695-34 67 21
A27: FRANK | B27: Frankenversand | C27: Peter Franken | D27: Marketing Manager | E27: Berliner Platz 43 | F27: München | H27: 80805 | I27: Germany | J27: 089-0877310
A28: FRANR | B28: France restauration | C28: Carine Schmitt | D28: Marketing Manager | E28: 54, rue Royale | F28: Nantes | H28: 44000 | I28: France | J28: 40.32.21.21
A29: FRANS | B29: Franchi S.p.A. | C29: Paolo Accorti | D29: Sales Representative | E29: Via Monte Bianco 34 | F29: Torino | H29: 10100 | I29: Italy | J29: 011-4988260
A30: FURIB | B30: Furia Bacalhau e Frutos do Mar | C30: Lino Rodriguez | D30: Sales Manager | E30: Jardim das rosas n. 32 | F30: Lisboa | H30: 1675 | I30: Portugal | J30: (1) 354-2534
A31: GALED | B31: Galería del gastrónomo | C31: Eduardo Saavedra | D31: Marketing Manager | E31: Rambla de Cataluña, 23 | F31: Barcelona | H31: 08022 | I31: Spain | J31: (93) 203 4560
A32: GODOS | B32: Godos Cocina Típica | C32: José Pedro Freyre | D32: Sales Manager | E32: C/ Romero, 33 | F32: Sevilla | H32: 41101 | I32: Spain | J32: (95) 555 82 82
A33: GOURL | B33: Gourmet Lanchonetes | C33: André Fonseca | D33: Sales Associate | E33: Av. Brasil, 442 | F33: Campinas | G33: SP | H33: 04876-786 | I33: Brazil | J33: (11) 555-9482
A34: GREAL | B34: Great Lakes Food Market | C34: Howard Snyder | D34: Marketing Manager | E34: 2732 Baker Blvd. | F34: Eugene | G34: OR | H34: 97403 | I34: USA | J34: (503) 555-7555
A35: GROSR | B35: GROSELLA-Restaurante | C35: Manuel Pereira | D35: Owner | E35: 5ª Ave. Los Palos Grandes | F35: Caracas | G35: DF | H35: 1081 | I35: Venezuela | J35: (2) 283-2951
A36: HANAR | B36: Hanari Carnes | C36: Mario Pontes | D36: Accounting Manager | E36: Rua do Paço, 67 | F36: Rio de Janeiro | G36: RJ | H36: 05454-876 | I36: Brazil | J36: (21) 555-0091
A37: HILAA | B37: HILARIÓN-Abastos | C37: Carlos Hernández | D37: Sales Representative | E37: Carrera 22 con Ave. Carlos Soublette #8-35 | F37: San Cristóbal | G37: Táchira | H37: 5022 | I37: Venezuela | J37: (5) 555-1340
A38: HUNGC | B38: Hungry Coyote Import Store | C38: Yoshi Latimer | D38: Sales Representative | E38: City Center Plaza 516 Main St. | F38: Elgin | G38: OR | H38: 97827 | I38: USA | J38: (503) 555-6874
A39: HUNGO | B39: Hungry Owl All-Night Grocers | C39: Patricia McKenna | D39: Sales Associate | E39: 8 Johnstown Road | F39: Cork | G39: Co. Cork | I39: Ireland | J39: 2967 542
A40: ISLAT | B40: Island Trading | C40: Helen Bennett | D40: Marketing Manager | E40: Garden House Crowther Way | F40: Cowes | G40: Isle of Wight | H40: PO31 7PJ | I40: UK | J40: (198) 555-8888
A41: KOENE | B41: Königlich Essen | C41: Philip Cramer | D41: Sales Associate | E41: Maubelstr. 90 | F41: Brandenburg | H41: 14776 | I41: Germany | J41: 0555-09876
A42: LACOR | B42: La corne d'abondance | C42: Daniel Tonini | D42: Sales Representative | E42: 67, avenue de l'Europe | F42: Versailles | H42: 78000 | I42: France | J42: 30.59.84.10
A43: LAMAI | B43: La maison d'Asie | C43: Annette Roulet | D43: Sales Manager | E43: 1 rue Alsace-Lorraine | F43: Toulouse | H43: 31000 | I43: France | J43: 61.77.61.10
A44: LAUGB | B44: Laughing Bacchus Wine Cellars | C44: Yoshi Tannamuri | D44: Marketing Assistant | E44: 1900 Oak St. | F44: Vancouver | G44: BC | H44: V3F 2K1 | I44: Canada | J44: (604) 555-3392
A45: LAZYK | B45: Lazy K Kountry Store | C45: John Steel | D45: Marketing Manager | E45: 12 Orchestra Terrace | F45: Walla Walla | G45: WA | H45: 99362 | I45: USA | J45: (509) 555-7969
A46: LEHMS | B46: Lehmanns Marktstand | C46: Renate Messner | D46: Sales Representative | E46: Magazinweg 7 | F46: Frankfurt a.M. | H46: 60528 | I46: Germany | J46: 069-0245984
A47: LETSS | B47: Let's Stop N Shop | C47: Jaime Yorres | D47: Owner | E47: 87 Polk St. Suite 5 | F47: San Francisco | G47: CA | H47: 94117 | I47: USA | J47: (415) 555-5938
A48: LILAS | B48: LILA-Supermercado | C48: Carlos González | D48: Accounting Manager | E48: Carrera 52 con Ave. Bolívar #65-98 Llano Largo | F48: Barquisimeto | G48: Lara | H48: 3508 | I48: Venezuela | J48: (9) 331-6954
A49: LINOD | B49: LINO-Delicateses | C49: Felipe Izquierdo | D49: Owner | E49: Ave. 5 de Mayo Porlamar | F49: I. de Margarita | G49: Nueva Esparta | H49: 4980 | I49: Venezuela | J49: (8) 34-56-12
A50: LONEP | B50: Lonesome Pine Restaurant | C50: Fran Wilson | D50: Sales Manager | E50: 89 Chiaroscuro Rd. | F50: Portland | G50: OR | H50: 97219 | I50: USA | J50: (503) 555-9573
A51: MAGAA | B51: Magazzini Alimentari Riuniti | C51: Giovanni Rovelli | D51: Marketing Manager | E51: Via Ludovico il Moro 22 | F51: Bergamo | H51: 24100 | I51: Italy | J51: 035-640230
A52: MAISD | B52: Maison Dewey | C52: Catherine Dewey | D52: Sales Agent | E52: Rue Joseph-Bens 532 | F52: Bruxelles | H52: B-1180 | I52: Belgium | J52: (02) 201 24 67
A53: MEREP | B53: Mère Paillarde | C53: Jean Fresnière | D53: Marketing Assistant | E53: 43 rue St. Laurent | F53: Montréal | G53: Québec | H53: H1J 1C3 | I53: Canada | J53: (514) 555-8054
A54: MORGK | B54: Morgenstern Gesundkost | C54: Alexander Feuer | D54: Marketing Assistant | E54: Heerstr. 22 | F54: Leipzig | H54: 04179 | I54: Germany | J54: 0342-023176
A55: NORTS | B55: North/South | C55: Simon Crowther | D55: Sales Associate | E55: South House 300 Queensbridge | F55: London | H55: SW7 1RZ | I55: UK | J55: (171) 555-7733
A56: OCEAN | B56: Océano Atlántico Ltda. | C56: Yvonne Moncada | D56: Sales Agent | E56: Ing. Gustavo Moncada 8585 Piso 20-A | F56: Buenos Aires | H56: 1010 | I56: Argentina | J56: (1) 135-5333
A57: OLDWO | B57: Old World Delicatessen | C57: Rene Phillips | D57: Sales Representative | E57: 2743 Bering St. | F57: Anchorage | G57: AK | H57: 99508 | I57: USA | J57: (907) 555-7584
A58: OTTIK | B58: Ottilies Käseladen | C58: Henriette Pfalzheim | D58: Owner | E58: Mehrheimerstr. 369 | F58: Köln | H58: 50739 | I58: Germany | J58: 0221-0644327
A59: PARIS | B59: Paris spécialités | C59: Marie Bertrand | D59: Owner | E59: 265, boulevard Charonne | F59: Paris | H59: 75012 | I59: France | J59: (1) 42.34.22.66
A60: PERIC | B60: Pericles Comidas clásicas | C60: Guillermo Fernández | D60: Sales Representative | E60: Calle Dr. Jorge Cash 321 | F60: México D.F. | H60: 05033 | I60: Mexico | J60: (5) 552-3745
A61: PICCO | B61: Piccolo und mehr | C61: Georg Pipps | D61: Sales Manager | E61: Geislweg 14 | F61: Salzburg | H61: 5020 | I61: Austria | J61: 6562-9722
A62: PRINI | B62: Princesa Isabel Vinhos | C62: Isabel de Castro | D62: Sales Representative | E62: Estrada da saúde n. 58 | F62: Lisboa | H62: 1756 | I62: Portugal | J62: (1) 356-5634
A63: QUEDE | B63: Que Delícia | C63: Bernardo Batista | D63: Accounting Manager | E63: Rua da Panificadora, 12 | F63: Rio de Janeiro | G63: RJ | H63: 02389-673 | I63: Brazil | J63: (21) 555-4252
A64: QUEEN | B64: Queen Cozinha | C64: Lúcia Carvalho | D64: Marketing Assistant | E64: Alameda dos Canàrios, 891 | F64: São Paulo | G64: SP | H64: 05487-020 | I64: Brazil | J64: (11) 555-1189
A65: QUICK | B65: QUICK-Stop | C65: Horst Kloss | D65: Accounting Manager | E65: Taucherstraße 10 | F65: Cunewalde | H65: 01307 | I65: Germany | J65: 0372-035188
A66: RANCH | B66: Rancho grande | C66: Sergio Gutiérrez | D66: Sales Representative | E66: Av. del Libertador 900 | F66: Buenos Aires | H66: 1010 | I66: Argentina | J66: (1) 123-5555
A67: RATTC | B67: Rattlesnake Canyon Grocery | C67: Paula Wilson | D67: Assistant Sales Representative | E67: 2817 Milton Dr. | F67: Albuquerque | G67: NM | H67: 87110 | I67: USA | J67: (505) 555-5939
A68: REGGC | B68: Reggiani Caseifici | C68: Maurizio Moroni | D68: Sales Associate | E68: Strada Provinciale 124 | F68: Reggio Emilia | H68: 42100 | I68: Italy | J68: 0522-556721
A69: RICAR | B69: Ricardo Adocicados | C69: Janete Limeira | D69: Assistant Sales Agent | E69: Av. Copacabana, 267 | F69: Rio de Janeiro | G69: RJ | H69: 02389-890 | I69: Brazil | J69: (21) 555-3412
A70: RICSU | B70: Richter Supermarkt | C70: Michael Holz | D70: Sales Manager | E70: Grenzacherweg 237 | F70: Genève | H70: 1203 | I70: Switzerland | J70: 0897-034214
A71: ROMEY | B71: Romero y tomillo | C71: Alejandra Camino | D71: Accounting Manager | E71: Gran Vía, 1 | F71: Madrid | H71: 28001 | I71: Spain | J71: (91) 745 6200
A72: SANTG | B72: Santé Gourmet | C72: Jonas Bergulfsen | D72: Owner | E72: Erling Skakkes gate 78 | F72: Stavern | H72: 4110 | I72: Norway | J72: 07-98 92 35
A73: SAVEA | B73: Save-a-lot Markets | C73: Jose Pavarotti | D73: Sales Representative | E73: 187 Suffolk Ln. | F73: Boise | G73: ID | H73: 83720 | I73: USA | J73: (208) 555-8097
A74: SEVES | B74: Seven Seas Imports | C74: Hari Kumar | D74: Sales Manager | E74: 90 Wadhurst Rd. | F74: London | H74: OX15 4NB | I74: UK | J74: (171) 555-1717
A75: SIMOB | B75: Simons bistro | C75: Jytte Petersen | D75: Owner | E75: Vinbæltet 34 | F75: København | H75: 1734 | I75: Denmark | J75: 31 12 34 56
A76: SPECD | B76: Spécialités du monde | C76: Dominique Perrier | D76: Marketing Manager | E76: 25, rue Lauriston | F76: Paris | H76: 75016 | I76: France | J76: (1) 47.55.60.10
A77: SPLIR | B77: Split Rail Beer & Ale | C77: Art Braunschweiger | D77: Sales Manager | E77: P.O. Box 555 | F77: Lander | G77: WY | H77: 82520 | I77: USA | J77: (307) 555-4680
A78: SUPRD | B78: Suprêmes délices | C78: Pascale Cartrain | D78: Accounting Manager | E78: Boulevard Tirou, 255 | F78: Charleroi | H78: B-6000 | I78: Belgium | J78: (071) 23 67 22 20
A79: THEBI | B79: The Big Cheese | C79: Liz Nixon | D79: Marketing Manager | E79: 89 Jefferson Way Suite 2 | F79: Portland | G79: OR | H79: 97201 | I79: USA | J79: (503) 555-3612
A80: THECR | B80: The Cracker Box | C80: Liu Wong | D80: Marketing Assistant | E80: 55 Grizzly Peak Rd. | F80: Butte | G80: MT | H80: 59801 | I80: USA | J80: (406) 555-5834
A81: TOMSP | B81: Toms Spezialitäten | C81: Karin Josephs | D81: Marketing Manager | E81: Luisenstr. 48 | F81: Münster | H81: 44087 | I81: Germany | J81: 0251-031259
A82: TORTU | B82: Tortuga Restaurante | C82: Miguel Angel Paolino | D82: Owner | E82: Avda. Azteca 123 | F82: México D.F. | H82: 05033 | I82: Mexico | J82: (5) 555-2933
A83: TRADH | B83: Tradição Hipermercados | C83: Anabela Domingues | D83: Sales Representative | E83: Av. Inês de Castro, 414 | F83: São Paulo | G83: SP | H83: 05634-030 | I83: Brazil | J83: (11) 555-2167
A84: TRAIH | B84: Trail's Head Gourmet Provisioners | C84: Helvetius Nagy | D84: Sales Associate | E84: 722 DaVinci Blvd. | F84: Kirkland | G84: WA | H84: 98034 | I84: USA | J84: (206) 555-8257
A85: VAFFE | B85: Vaffeljernet | C85: Palle Ibsen | D85: Sales Manager | E85: Smagsløget 45 | F85: Århus | H85: 8200 | I85: Denmark | J85: 86 21 32 43
A86: VICTE | B86: Victuailles en stock | C86: Mary Saveley | D86: Sales Agent | E86: 2, rue du Commerce | F86: Lyon | H86: 69004 | I86: France | J86: 78.32.54.86
A87: VINET | B87: Vins et alcools Chevalier | C87: Paul Henriot | D87: Accounting Manager | E87: 59 rue de l'Abbaye | F87: Reims | H87: 51100 | I87: France | J87: 26.47.15.10
A88: WANDK | B88: Die Wandernde Kuh | C88: Rita Müller | D88: Sales Representative | E88: Adenauerallee 900 | F88: Stuttgart | H88: 70563 | I88: Germany | J88: 0711-020361
A89: WARTH | B89: Wartian Herkku | C89: Pirkko Koskitalo | D89: Accounting Manager | E89: Torikatu 38 | F89: Oulu | H89: 90110 | I89: Finland | J89: 981-443655
A90: WELLI | B90: Wellington Importadora | C90: Paula Parente | D90: Sales Manager | E90: Rua do Mercado, 12 | F90: Resende | G90: SP | H90: 08737-363 | I90: Brazil | J90: (14) 555-8122
A91: WHITC | B91: White Clover Markets | C91: Karl Jablonski | D91: Owner | E91: 305 - 14th Ave. S. Suite 3B | F91: Seattle | G91: WA | H91: 98128 | I91: USA | J91: (206) 555-4112
A92: WILMK | B92: Wilman Kala | C92: Matti Karttunen | D92: Owner/Marketing Assistant | E92: Keskuskatu 45 | F92: Helsinki | H92: 21240 | I92: Finland | J92: 90-224 8858
A93: WOLZA | B93: Wolski Zajazd | C93: Zbyszek Piestrzeniewicz | D93: Owner | E93: ul. Filtrowa 68 | F93: Warszawa | H93: 01-012 | I93: Poland | J93: (26) 642-7012

Sheet employees
A1: EmployeeID | B1: LastName | C1: FirstName | D1: Fullname | E1: Title | F1: TitleOfCourtesy | G1: BirthDate | H1: HireDate | I1: Address | J1: City | K1: Region | L1: PostalCode | M1: Country | N1: HomePhone | O1: Extension | P1: Notes | Q1: ReportsTo | R1: Hire year
A2: 1 | B2: Davolio | C2: Nancy | D2: =_xlfn.CONCAT(employees[[#This Row],[FirstName]], " ", employees[[#This Row],[LastName]]) -> Nancy Davolio | E2: Sales Representative | F2: Ms. | G2: 17875 | H2: 33725 | I2: 507 - 20th Ave. E. Apt. 2A | J2: Seattle | K2: WA | L2: 98122 | M2: USA | N2: (206) 555-9857 | O2: 5467 | P2: Education includes a BA in psychology from Colorado State University in 1970. She also completed "The Art of the Cold Call." Nancy is a member of Toastmasters International. | Q2: 2 | R2: =YEAR(employees[[#This Row],[HireDate]]) -> 1992
A3: 2 | B3: Fuller | C3: Andrew | D3: =_xlfn.CONCAT(employees[[#This Row],[FirstName]], " ", employees[[#This Row],[LastName]]) -> Andrew Fuller | E3: Vice President, Sales | F3: Dr. | G3: 19043 | H3: 33830 | I3: 908 W. Capital Way | J3: Tacoma | K3: WA | L3: 98401 | M3: USA | N3: (206) 555-9482 | O3: 3457 | P3: Andrew received his BTS commercial in 1974 and a Ph.D. in international marketing from the University of Dallas in 1981. He is fluent in French and Italian and reads German. He joined the company as a sales representative, was promoted to sales manager in January 1992 and to vice president of sales in March 1993. Andrew is a member of the Sales Management Roundtable, the Seattle Chamber of Commerce, and the Pacific Rim Importers Association. | R3: =YEAR(employees[[#This Row],[HireDate]]) -> 1992
A4: 3 | B4: Leverling | C4: Janet | D4: =_xlfn.CONCAT(employees[[#This Row],[FirstName]], " ", employees[[#This Row],[LastName]]) -> Janet Leverling | E4: Sales Representative | F4: Ms. | G4: 23253 | H4: 33695 | I4: 722 Moss Bay Blvd. | J4: Kirkland | K4: WA | L4: 98033 | M4: USA | N4: (206) 555-3412 | O4: 3355 | P4: Janet has a BS degree in chemistry from Boston College (1984). She has also completed a certificate program in food retailing management. Janet was hired as a sales associate in 1991 and promoted to sales representative in February 1992. | Q4: 2 | R4: =YEAR(employees[[#This Row],[HireDate]]) -> 1992
A5: 4 | B5: Peacock | C5: Margaret | D5: =_xlfn.CONCAT(employees[[#This Row],[FirstName]], " ", employees[[#This Row],[LastName]]) -> Margaret Peacock | E5: Sales Representative | F5: Mrs. | G5: 13777 | H5: 34092 | I5: 4110 Old Redmond Rd. | J5: Redmond | K5: WA | L5: 98052 | M5: USA | N5: (206) 555-8122 | O5: 5176 | P5: Margaret holds a BA in English literature from Concordia College (1958) and an MA from the American Institute of Culinary Arts (1966). She was assigned to the London office temporarily from July through November 1992. | Q5: 2 | R5: =YEAR(employees[[#This Row],[HireDate]]) -> 1993
A6: 5 | B6: Buchanan | C6: Steven | D6: =_xlfn.CONCAT(employees[[#This Row],[FirstName]], " ", employees[[#This Row],[LastName]]) -> Steven Buchanan | E6: Sales Manager | F6: Mr. | G6: 20152 | H6: 34259 | I6: 14 Garrett Hill | J6: London | L6: SW1 8JR | M6: UK | N6: (71) 555-4848 | O6: 3453 | P6: Steven Buchanan graduated from St. Andrews University, Scotland, with a BSC degree in 1976. Upon joining the company as a sales representative in 1992, he spent 6 months in an orientation program at the Seattle office and then returned to his permanent post in London. He was promoted to sales manager in March 1993. Mr. Buchanan has completed the courses "Successful Telemarketing" and "International Sales Management." He is fluent in French. | Q6: 2 | R6: =YEAR(employees[[#This Row],[HireDate]]) -> 1993
A7: 6 | B7: Suyama | C7: Michael | D7: =_xlfn.CONCAT(employees[[#This Row],[FirstName]], " ", employees[[#This Row],[LastName]]) -> Michael Suyama | E7: Sales Representative | F7: Mr. | G7: 23194 | H7: 34259 | I7: Coventry House Miner Rd. | J7: London | L7: EC2 7JR | M7: UK | N7: (71) 555-7773 | O7: 428 | P7: Michael is a graduate of Sussex University (MA, economics, 1983) and the University of California at Los Angeles (MBA, marketing, 1986). He has also taken the courses "Multi-Cultural Selling" and "Time Management for the Sales Professional." He is fluent in Japanese and can read and write French, Portuguese, and Spanish. | Q7: 5 | R7: =YEAR(employees[[#This Row],[HireDate]]) -> 1993
A8: 7 | B8: King | C8: Robert | D8: =_xlfn.CONCAT(employees[[#This Row],[FirstName]], " ", employees[[#This Row],[LastName]]) -> Robert King | E8: Sales Representative | F8: Mr. | G8: 22065 | H8: 34336 | I8: Edgeham Hollow Winchester Way | J8: London | L8: RG1 9SP | M8: UK | N8: (71) 555-5598 | O8: 465 | P8: Robert King served in the Peace Corps and traveled extensively before completing his degree in English at the University of Michigan in 1992, the year he joined the company. After completing a course entitled "Selling in Europe," he was transferred to the London office in March 1993. | Q8: 5 | R8: =YEAR(employees[[#This Row],[HireDate]]) -> 1994
A9: 8 | B9: Callahan | C9: Laura | D9: =_xlfn.CONCAT(employees[[#This Row],[FirstName]], " ", employees[[#This Row],[LastName]]) -> Laura Callahan | E9: Inside Sales Coordinator | F9: Ms. | G9: 21194 | H9: 34398 | I9: 4726 - 11th Ave. N.E. | J9: Seattle | K9: WA | L9: 98105 | M9: USA | N9: (206) 555-1189 | O9: 2344 | P9: Laura received a BA in psychology from the University of Washington. She has also completed a course in business French. She reads and writes French. | Q9: 2 | R9: =YEAR(employees[[#This Row],[HireDate]]) -> 1994
A10: 9 | B10: Dodsworth | C10: Anne | D10: =_xlfn.CONCAT(employees[[#This Row],[FirstName]], " ", employees[[#This Row],[LastName]]) -> Anne Dodsworth | E10: Sales Representative | F10: Ms. | G10: 24134 | H10: 34653 | I10: 7 Houndstooth Rd. | J10: London | L10: WG2 7LT | M10: UK | N10: (71) 555-4444 | O10: 452 | P10: Anne has a BA degree in English from St. Lawrence College. She is fluent in French and German. | Q10: 5 | R10: =YEAR(employees[[#This Row],[HireDate]]) -> 1994

Sheet orders
A1: OrderID | B1: CustomerID | C1: EmployeeID | D1: OrderDate | E1: RequiredDate | F1: ShippedDate | G1: ShipVia | H1: Freight | I1: ShipName | J1: ShipAddress | K1: ShipCity | L1: ShipRegion | M1: ShipPostalCode | N1: ShipCountry | O1: month | P1: month number | Q1: year
A2: 10248 | B2: VINET | C2: 5 | D2: 34550 | E2: 34578 | F2: 34562 | G2: 3 | H2: 32.38 | I2: Vins et alcools Chevalier | J2: 59 rue de l'Abbaye | K2: Reims | M2: 51100 | N2: France | O2: =TEXT(orders[[#This Row],[OrderDate]],"mmm") -> Aug | P2: =MONTH(orders[[#This Row],[OrderDate]]) -> 8 | Q2: =YEAR(orders[[#This Row],[OrderDate]]) -> 1994
A3: 10249 | B3: TOMSP | C3: 6 | D3: 34551 | E3: 34593 | F3: 34556 | G3: 1 | H3: 11.61 | I3: Toms Spezialitäten | J3: Luisenstr. 48 | K3: Münster | M3: 44087 | N3: Germany | O3: =TEXT(orders[[#This Row],[OrderDate]],"mmm") -> Aug | P3: =MONTH(orders[[#This Row],[OrderDate]]) -> 8 | Q3: =YEAR(orders[[#This Row],[OrderDate]]) -> 1994
A4: 10250 | B4: HANAR | C4: 4 | D4: 34554 | E4: 34582 | F4: 34558 | G4: 2 | H4: 65.83 | I4: Hanari Carnes | J4: Rua do Paço, 67 | K4: Rio de Janeiro | L4: RJ | M4: 05454-876 | N4: Brazil | O4: =TEXT(orders[[#This Row],[OrderDate]],"mmm") -> Aug | P4: =MONTH(orders[[#This Row],[OrderDate]]) -> 8 | Q4: =YEAR(orders[[#This Row],[OrderDate]]) -> 1994
A5: 10251 | B5: VICTE | C5: 3 | D5: 34554 | E5: 34582 | F5: 34561 | G5: 1 | H5: 41.34 | I5: Victuailles en stock | J5: 2, rue du Commerce | K5: Lyon | M5: 69004 | N5: France | O5: =TEXT(orders[[#This Row],[OrderDate]],"mmm") -> Aug | P5: =MONTH(orders[[#This Row],[OrderDate]]) -> 8 | Q5: =YEAR(orders[[#This Row],[OrderDate]]) -> 1994
A6: 10252 | B6: SUPRD | C6: 4 | D6: 34555 | E6: 34583 | F6: 34557 | G6: 2 | H6: 51.3 | I6: Suprêmes délices | J6: Boulevard Tirou, 255 | K6: Charleroi | M6: B-6000 | N6: Belgium | O6: =TEXT(orders[[#This Row],[OrderDate]],"mmm") -> Aug | P6: =MONTH(orders[[#This Row],[OrderDate]]) -> 8 | Q6: =YEAR(orders[[#This Row],[OrderDate]]) -> 1994
A7: 10253 | B7: HANAR | C7: 3 | D7: 34556 | E7: 34570 | F7: 34562 | G7: 2 | H7: 58.17 | I7: Hanari Carnes | J7: Rua do Paço, 67 | K7: Rio de Janeiro | L7: RJ | M7: 05454-876 | N7: Brazil | O7: =TEXT(orders[[#This Row],[OrderDate]],"mmm") -> Aug | P7: =MONTH(orders[[#This Row],[OrderDate]]) -> 8 | Q7: =YEAR(orders[[#This Row],[OrderDate]]) -> 1994
A8: 10254 | B8: CHOPS | C8: 5 | D8: 34557 | E8: 34585 | F8: 34569 | G8: 2 | H8: 22.98 | I8: Chop-suey Chinese | J8: Hauptstr. 31 | K8: Bern | M8: 3012 | N8: Switzerland | O8: =TEXT(orders[[#This Row],[OrderDate]],"mmm") -> Aug | P8: =MONTH(orders[[#This Row],[OrderDate]]) -> 8 | Q8: =YEAR(orders[[#This Row],[OrderDate]]) -> 1994
A9: 10255 | B9: RICSU | C9: 9 | D9: 34558 | E9: 34586 | F9: 34561 | G9: 3 | H9: 148.33 | I9: Richter Supermarkt | J9: Starenweg 5 | K9: Genève | M9: 1204 | N9: Switzerland | O9: =TEXT(orders[[#This Row],[OrderDate]],"mmm") -> Aug | P9: =MONTH(orders[[#This Row],[OrderDate]]) -> 8 | Q9: =YEAR(orders[[#This Row],[OrderDate]]) -> 1994
A10: 10256 | B10: WELLI | C10: 3 | D10: 34561 | E10: 34589 | F10: 34563 | G10: 2 | H10: 13.97 | I10: Wellington Importadora | J10: Rua do Mercado, 12 | K10: Resende | L10: SP | M10: 08737-363 | N10: Brazil | O10: =TEXT(orders[[#This Row],[OrderDate]],"mmm") -> Aug | P10: =MONTH(orders[[#This Row],[OrderDate]]) -> 8 | Q10: =YEAR(orders[[#This Row],[OrderDate]]) -> 1994
A11: 10257 | B11: HILAA | C11: 4 | D11: 34562 | E11: 34590 | F11: 34568 | G11: 3 | H11: 81.91 | I11: HILARIÓN-Abastos | J11: Carrera 22 con Ave. Carlos Soublette #8-35 | K11: San Cristóbal | L11: Táchira | M11: 5022 | N11: Venezuela | O11: =TEXT(orders[[#This Row],[OrderDate]],"mmm") -> Aug | P11: =MONTH(orders[[#This Row],[OrderDate]]) -> 8 | Q11: =YEAR(orders[[#This Row],[OrderDate]]) -> 1994
A12: 10258 | B12: ERNSH | C12: 1 | D12: 34563 | E12: 34591 | F12: 34569 | G12: 1 | H12: 140.51 | I12: Ernst Handel | J12: Kirchgasse 6 | K12: Graz | M12: 8010 | N12: Austria | O12: =TEXT(orders[[#This Row],[OrderDate]],"mmm") -> Aug | P12: =MONTH(orders[[#This Row],[OrderDate]]) -> 8 | Q12: =YEAR(orders[[#This Row],[OrderDate]]) -> 1994
A13: 10259 | B13: CENTC | C13: 4 | D13: 34564 | E13: 34592 | F13: 34571 | G13: 3 | H13: 3.25 | I13: Centro comercial Moctezuma | J13: Sierras de Granada 9993 | K13: México D.F. | M13: 05022 | N13: Mexico | O13: =TEXT(orders[[#This Row],[OrderDate]],"mmm") -> Aug | P13: =MONTH(orders[[#This Row],[OrderDate]]) -> 8 | Q13: =YEAR(orders[[#This Row],[OrderDate]]) -> 1994
A14: 10260 | B14: OTTIK | C14: 4 | D14: 34565 | E14: 34593 | F14: 34575 | G14: 1 | H14: 55.09 | I14: Ottilies Käseladen | J14: Mehrheimerstr. 369 | K14: Köln | M14: 50739 | N14: Germany | O14: =TEXT(orders[[#This Row],[OrderDate]],"mmm") -> Aug | P14: =MONTH(orders[[#This Row],[OrderDate]]) -> 8 | Q14: =YEAR(orders[[#This Row],[OrderDate]]) -> 1994
A15: 10261 | B15: QUEDE | C15: 4 | D15: 34565 | E15: 34593 | F15: 34576 | G15: 2 | H15: 3.05 | I15: Que Delícia | J15: Rua da Panificadora, 12 | K15: Rio de Janeiro | L15: RJ | M15: 02389-673 | N15: Brazil | O15: =TEXT(orders[[#This Row],[OrderDate]],"mmm") -> Aug | P15: =MONTH(orders[[#This Row],[OrderDate]]) -> 8 | Q15: =YEAR(orders[[#This Row],[OrderDate]]) -> 1994
A16: 10262 | B16: RATTC | C16: 8 | D16: 34568 | E16: 34596 | F16: 34571 | G16: 3 | H16: 48.29 | I16: Rattlesnake Canyon Grocery | J16: 2817 Milton Dr. | K16: Albuquerque | L16: NM | M16: 87110 | N16: USA | O16: =TEXT(orders[[#This Row],[OrderDate]],"mmm") -> Aug | P16: =MONTH(orders[[#This Row],[OrderDate]]) -> 8 | Q16: =YEAR(orders[[#This Row],[OrderDate]]) -> 1994
A17: 10263 | B17: ERNSH | C17: 9 | D17: 34569 | E17: 34597 | F17: 34577 | G17: 3 | H17: 146.06 | I17: Ernst Handel | J17: Kirchgasse 6 | K17: Graz | M17: 8010 | N17: Austria | O17: =TEXT(orders[[#This Row],[OrderDate]],"mmm") -> Aug | P17: =MONTH(orders[[#This Row],[OrderDate]]) -> 8 | Q17: =YEAR(orders[[#This Row],[OrderDate]]) -> 1994
A18: 10264 | B18: FOLKO | C18: 6 | D18: 34570 | E18: 34598 | F18: 34600 | G18: 3 | H18: 3.67 | I18: Folk och fä HB | J18: Åkergatan 24 | K18: Bräcke | M18: S-844 67 | N18: Sweden | O18: =TEXT(orders[[#This Row],[OrderDate]],"mmm") -> Aug | P18: =MONTH(orders[[#This Row],[OrderDate]]) -> 8 | Q18: =YEAR(orders[[#This Row],[OrderDate]]) -> 1994
A19: 10265 | B19: BLONP | C19: 2 | D19: 34571 | E19: 34599 | F19: 34589 | G19: 1 | H19: 55.28 | I19: Blondel père et fils | J19: 24, place Kléber | K19: Strasbourg | M19: 67000 | N19: France | O19: =TEXT(orders[[#This Row],[OrderDate]],"mmm") -> Aug | P19: =MONTH(orders[[#This Row],[OrderDate]]) -> 8 | Q19: =YEAR(orders[[#This Row],[OrderDate]]) -> 1994
A20: 10266 | B20: WARTH | C20: 3 | D20: 34572 | E20: 34614 | F20: 34577 | G20: 3 | H20: 25.73 | I20: Wartian Herkku | J20: Torikatu 38 | K20: Oulu | M20: 90110 | N20: Finland | O20: =TEXT(orders[[#This Row],[OrderDate]],"mmm") -> Aug | P20: =MONTH(orders[[#This Row],[OrderDate]]) -> 8 | Q20: =YEAR(orders[[#This Row],[OrderDate]]) -> 1994
A21: 10267 | B21: FRANK | C21: 4 | D21: 34575 | E21: 34603 | F21: 34583 | G21: 1 | H21: 208.58 | I21: Frankenversand | J21: Berliner Platz 43 | K21: München | M21: 80805 | N21: Germany | O21: =TEXT(orders[[#This Row],[OrderDate]],"mmm") -> Aug | P21: =MONTH(orders[[#This Row],[OrderDate]]) -> 8 | Q21: =YEAR(orders[[#This Row],[OrderDate]]) -> 1994
A22: 10268 | B22: GROSR | C22: 8 | D22: 34576 | E22: 34604 | F22: 34579 | G22: 3 | H22: 66.29 | I22: GROSELLA-Restaurante | J22: 5ª Ave. Los Palos Grandes | K22: Caracas | L22: DF | M22: 1081 | N22: Venezuela | O22: =TEXT(orders[[#This Row],[OrderDate]],"mmm") -> Aug | P22: =MONTH(orders[[#This Row],[OrderDate]]) -> 8 | Q22: =YEAR(orders[[#This Row],[OrderDate]]) -> 1994
A23: 10269 | B23: WHITC | C23: 5 | D23: 34577 | E23: 34591 | F23: 34586 | G23: 1 | H23: 4.56 | I23: White Clover Markets | J23: 1029 - 12th Ave. S. | K23: Seattle | L23: WA | M23: 98124 | N23: USA | O23: =TEXT(orders[[#This Row],[OrderDate]],"mmm") -> Aug | P23: =MONTH(orders[[#This Row],[OrderDate]]) -> 8 | Q23: =YEAR(orders[[#This Row],[OrderDate]]) -> 1994
A24: 10270 | B24: WARTH | C24: 1 | D24: 34578 | E24: 34606 | F24: 34579 | G24: 1 | H24: 136.54 | I24: Wartian Herkku | J24: Torikatu 38 | K24: Oulu | M24: 90110 | N24: Finland | O24: =TEXT(orders[[#This Row],[OrderDate]],"mmm") -> Sep | P24: =MONTH(orders[[#This Row],[OrderDate]]) -> 9 | Q24: =YEAR(orders[[#This Row],[OrderDate]]) -> 1994
A25: 10271 | B25: SPLIR | C25: 6 | D25: 34578 | E25: 34606 | F25: 34607 | G25: 2 | H25: 4.54 | I25: Split Rail Beer & Ale | J25: P.O. Box 555 | K25: Lander | L25: WY | M25: 82520 | N25: USA | O25: =TEXT(orders[[#This Row],[OrderDate]],"mmm") -> Sep | P25: =MONTH(orders[[#This Row],[OrderDate]]) -> 9 | Q25: =YEAR(orders[[#This Row],[OrderDate]]) -> 1994
A26: 10272 | B26: RATTC | C26: 6 | D26: 34579 | E26: 34607 | F26: 34583 | G26: 2 | H26: 98.03 | I26: Rattlesnake Canyon Grocery | J26: 2817 Milton Dr. | K26: Albuquerque | L26: NM | M26: 87110 | N26: USA | O26: =TEXT(orders[[#This Row],[OrderDate]],"mmm") -> Sep | P26: =MONTH(orders[[#This Row],[OrderDate]]) -> 9 | Q26: =YEAR(orders[[#This Row],[OrderDate]]) -> 1994
A27: 10273 | B27: QUICK | C27: 3 | D27: 34582 | E27: 34610 | F27: 34589 | G27: 3 | H27: 76.07 | I27: QUICK-Stop | J27: Taucherstraße 10 | K27: Cunewalde | M27: 01307 | N27: Germany | O27: =TEXT(orders[[#This Row],[OrderDate]],"mmm") -> Sep | P27: =MONTH(orders[[#This Row],[OrderDate]]) -> 9 | Q27: =YEAR(orders[[#This Row],[OrderDate]]) -> 1994
A28: 10274 | B28: VINET | C28: 6 | D28: 34583 | E28: 34611 | F28: 34593 | G28: 1 | H28: 6.01 | I28: Vins et alcools Chevalier | J28: 59 rue de l'Abbaye | K28: Reims | M28: 51100 | N28: France | O28: =TEXT(orders[[#This Row],[OrderDate]],"mmm") -> Sep | P28: =MONTH(orders[[#This Row],[OrderDate]]) -> 9 | Q28: =YEAR(orders[[#This Row],[OrderDate]]) -> 1994
A29: 10275 | B29: MAGAA | C29: 1 | D29: 34584 | E29: 34612 | F29: 34586 | G29: 1 | H29: 26.93 | I29: Magazzini Alimentari Riuniti | J29: Via Ludovico il Moro 22 | K29: Bergamo | M29: 24100 | N29: Italy | O29: =TEXT(orders[[#This Row],[OrderDate]],"mmm") -> Sep | P29: =MONTH(orders[[#This Row],[OrderDate]]) -> 9 | Q29: =YEAR(orders[[#This Row],[OrderDate]]) -> 1994
A30: 10276 | B30: TORTU | C30: 8 | D30: 34585 | E30: 34599 | F30: 34591 | G30: 3 | H30: 13.84 | I30: Tortuga Restaurante | J30: Avda. Azteca 123 | K30: México D.F. | M30: 05033 | N30: Mexico | O30: =TEXT(orders[[#This Row],[OrderDate]],"mmm") -> Sep | P30: =MONTH(orders[[#This Row],[OrderDate]]) -> 9 | Q30: =YEAR(orders[[#This Row],[OrderDate]]) -> 1994
A31: 10277 | B31: MORGK | C31: 2 | D31: 34586 | E31: 34614 | F31: 34590 | G31: 3 | H31: 125.77 | I31: Morgenstern Gesundkost | J31: Heerstr. 22 | K31: Leipzig | M31: 04179 | N31: Germany | O31: =TEXT(orders[[#This Row],[OrderDate]],"mmm") -> Sep | P31: =MONTH(orders[[#This Row],[OrderDate]]) -> 9 | Q31: =YEAR(orders[[#This Row],[OrderDate]]) -> 1994
A32: 10278 | B32: BERGS | C32: 8 | D32: 34589 | E32: 34617 | F32: 34593 | G32: 2 | H32: 92.69 | I32: Berglunds snabbköp | J32: Berguvsvägen 8 | K32: Luleå | M32: S-958 22 | N32: Sweden | O32: =TEXT(orders[[#This Row],[OrderDate]],"mmm") -> Sep | P32: =MONTH(orders[[#This Row],[OrderDate]]) -> 9 | Q32: =YEAR(orders[[#This Row],[OrderDate]]) -> 1994
A33: 10279 | B33: LEHMS | C33: 8 | D33: 34590 | E33: 34618 | F33: 34593 | G33: 2 | H33: 25.83 | I33: Lehmanns Marktstand | J33: Magazinweg 7 | K33: Frankfurt a.M. | M33: 60528 | N33: Germany | O33: =TEXT(orders[[#This Row],[OrderDate]],"mmm") -> Sep | P33: =MONTH(orders[[#This Row],[OrderDate]]) -> 9 | Q33: =YEAR(orders[[#This Row],[OrderDate]]) -> 1994
A34: 10280 | B34: BERGS | C34: 2 | D34: 34591 | E34: 34619 | F34: 34620 | G34: 1 | H34: 8.98 | I34: Berglunds snabbköp | J34: Berguvsvägen 8 | K34: Luleå | M34: S-958 22 | N34: Sweden | O34: =TEXT(orders[[#This Row],[OrderDate]],"mmm") -> Sep | P34: =MONTH(orders[[#This Row],[OrderDate]]) -> 9 | Q34: =YEAR(orders[[#This Row],[OrderDate]]) -> 1994
A35: 10281 | B35: ROMEY | C35: 4 | D35: 34591 | E35: 34605 | F35: 34598 | G35: 1 | H35: 2.94 | I35: Romero y tomillo | J35: Gran Vía, 1 | K35: Madrid | M35: 28001 | N35: Spain | O35: =TEXT(orders[[#This Row],[OrderDate]],"mmm") -> Sep | P35: =MONTH(orders[[#This Row],[OrderDate]]) -> 9 | Q35: =YEAR(orders[[#This Row],[OrderDate]]) -> 1994
A36: 10282 | B36: ROMEY | C36: 4 | D36: 34592 | E36: 34620 | F36: 34598 | G36: 1 | H36: 12.69 | I36: Romero y tomillo | J36: Gran Vía, 1 | K36: Madrid | M36: 28001 | N36: Spain | O36: =TEXT(orders[[#This Row],[OrderDate]],"mmm") -> Sep | P36: =MONTH(orders[[#This Row],[OrderDate]]) -> 9 | Q36: =YEAR(orders[[#This Row],[OrderDate]]) -> 1994
A37: 10283 | B37: LILAS | C37: 3 | D37: 34593 | E37: 34621 | F37: 34600 | G37: 3 | H37: 84.81 | I37: LILA-Supermercado | J37: Carrera 52 con Ave. Bolívar #65-98 Llano Largo | K37: Barquisimeto | L37: Lara | M37: 3508 | N37: Venezuela | O37: =TEXT(orders[[#This Row],[OrderDate]],"mmm") -> Sep | P37: =MONTH(orders[[#This Row],[OrderDate]]) -> 9 | Q37: =YEAR(orders[[#This Row],[OrderDate]]) -> 1994
A38: 10284 | B38: LEHMS | C38: 4 | D38: 34596 | E38: 34624 | F38: 34604 | G38: 1 | H38: 76.56 | I38: Lehmanns Marktstand | J38: Magazinweg 7 | K38: Frankfurt a.M. | M38: 60528 | N38: Germany | O38: =TEXT(orders[[#This Row],[OrderDate]],"mmm") -> Sep | P38: =MONTH(orders[[#This Row],[OrderDate]]) -> 9 | Q38: =YEAR(orders[[#This Row],[OrderDate]]) -> 1994
A39: 10285 | B39: QUICK | C39: 1 | D39: 34597 | E39: 34625 | F39: 34603 | G39: 2 | H39: 76.83 | I39: QUICK-Stop | J39: Taucherstraße 10 | K39: Cunewalde | M39: 01307 | N39: Germany | O39: =TEXT(orders[[#This Row],[OrderDate]],"mmm") -> Sep | P39: =MONTH(orders[[#This Row],[OrderDate]]) -> 9 | Q39: =YEAR(orders[[#This Row],[OrderDate]]) -> 1994
A40: 10286 | B40: QUICK | C40: 8 | D40: 34598 | E40: 34626 | F40: 34607 | G40: 3 | H40: 229.24 | I40: QUICK-Stop | J40: Taucherstraße 10 | K40: Cunewalde | M40: 01307 | N40: Germany | O40: =TEXT(orders[[#This Row],[OrderDate]],"mmm") -> Sep | P40: =MONTH(orders[[#This Row],[OrderDate]]) -> 9 | Q40: =YEAR(orders[[#This Row],[OrderDate]]) -> 1994
A41: 10287 | B41: RICAR | C41: 8 | D41: 34599 | E41: 34627 | F41: 34605 | G41: 3 | H41: 12.76 | I41: Ricardo Adocicados | J41: Av. Copacabana, 267 | K41: Rio de Janeiro | L41: RJ | M41: 02389-890 | N41: Brazil | O41: =TEXT(orders[[#This Row],[OrderDate]],"mmm") -> Sep | P41: =MONTH(orders[[#This Row],[OrderDate]]) -> 9 | Q41: =YEAR(orders[[#This Row],[OrderDate]]) -> 1994
A42: 10288 | B42: REGGC | C42: 4 | D42: 34600 | E42: 34628 | F42: 34611 | G42: 1 | H42: 7.45 | I42: Reggiani Caseifici | J42: Strada Provinciale 124 | K42: Reggio Emilia | M42: 42100 | N42: Italy | O42: =TEXT(orders[[#This Row],[OrderDate]],"mmm") -> Sep | P42: =MONTH(orders[[#This Row],[OrderDate]]) -> 9 | Q42: =YEAR(orders[[#This Row],[OrderDate]]) -> 1994
A43: 10289 | B43: BSBEV | C43: 7 | D43: 34603 | E43: 34631 | F43: 34605 | G43: 3 | H43: 22.77 | I43: B's Beverages | J43: Fauntleroy Circus | K43: London | M43: EC2 5NT | N43: UK | O43: =TEXT(orders[[#This Row],[OrderDate]],"mmm") -> Sep | P43: =MONTH(orders[[#This Row],[OrderDate]]) -> 9 | Q43: =YEAR(orders[[#This Row],[OrderDate]]) -> 1994
A44: 10290 | B44: COMMI | C44: 8 | D44: 34604 | E44: 34632 | F44: 34611 | G44: 1 | H44: 79.7 | I44: Comércio Mineiro | J44: Av. dos Lusíadas, 23 | K44: São Paulo | L44: SP | M44: 05432-043 | N44: Brazil | O44: =TEXT(orders[[#This Row],[OrderDate]],"mmm") -> Sep | P44: =MONTH(orders[[#This Row],[OrderDate]]) -> 9 | Q44: =YEAR(orders[[#This Row],[OrderDate]]) -> 1994
A45: 10291 | B45: QUEDE | C45: 6 | D45: 34604 | E45: 34632 | F45: 34612 | G45: 2 | H45: 6.4 | I45: Que Delícia | J45: Rua da Panificadora, 12 | K45: Rio de Janeiro | L45: RJ | M45: 02389-673 | N45: Brazil | O45: =TEXT(orders[[#This Row],[OrderDate]],"mmm") -> Sep | P45: =MONTH(orders[[#This Row],[OrderDate]]) -> 9 | Q45: =YEAR(orders[[#This Row],[OrderDate]]) -> 1994
A46: 10292 | B46: TRADH | C46: 1 | D46: 34605 | E46: 34633 | F46: 34610 | G46: 2 | H46: 1.35 | I46: Tradição Hipermercados | J46: Av. Inês de Castro, 414 | K46: São Paulo | L46: SP | M46: 05634-030 | N46: Brazil | O46: =TEXT(orders[[#This Row],[OrderDate]],"mmm") -> Sep | P46: =MONTH(orders[[#This Row],[OrderDate]]) -> 9 | Q46: =YEAR(orders[[#This Row],[OrderDate]]) -> 1994
A47: 10293 | B47: TORTU | C47: 1 | D47: 34606 | E47: 34634 | F47: 34619 | G47: 3 | H47: 21.18 | I47: Tortuga Restaurante | J47: Avda. Azteca 123 | K47: México D.F. | M47: 05033 | N47: Mexico | O47: =TEXT(orders[[#This Row],[OrderDate]],"mmm") -> Sep | P47: =MONTH(orders[[#This Row],[OrderDate]]) -> 9 | Q47: =YEAR(orders[[#This Row],[OrderDate]]) -> 1994
A48: 10294 | B48: RATTC | C48: 4 | D48: 34607 | E48: 34635 | F48: 34613 | G48: 2 | H48: 147.26 | I48: Rattlesnake Canyon Grocery | J48: 2817 Milton Dr. | K48: Albuquerque | L48: NM | M48: 87110 | N48: USA | O48: =TEXT(orders[[#This Row],[OrderDate]],"mmm") -> Sep | P48: =MONTH(orders[[#This Row],[OrderDate]]) -> 9 | Q48: =YEAR(orders[[#This Row],[OrderDate]]) -> 1994
A49: 10295 | B49: VINET | C49: 2 | D49: 34610 | E49: 34638 | F49: 34618 | G49: 2 | H49: 1.15 | I49: Vins et alcools Chevalier | J49: 59 rue de l'Abbaye | K49: Reims | M49: 51100 | N49: France | O49: =TEXT(orders[[#This Row],[OrderDate]],"mmm") -> Oct | P49: =MONTH(orders[[#This Row],[OrderDate]]) -> 10 | Q49: =YEAR(orders[[#This Row],[OrderDate]]) -> 1994
A50: 10296 | B50: LILAS | C50: 6 | D50: 34611 | E50: 34639 | F50: 34619 | G50: 1 | H50: 0.12 | I50: LILA-Supermercado | J50: Carrera 52 con Ave. Bolívar #65-98 Llano Largo | K50: Barquisimeto | L50: Lara | M50: 3508 | N50: Venezuela | O50: =TEXT(orders[[#This Row],[OrderDate]],"mmm") -> Oct | P50: =MONTH(orders[[#This Row],[OrderDate]]) -> 10 | Q50: =YEAR(orders[[#This Row],[OrderDate]]) -> 1994
A51: 10297 | B51: BLONP | C51: 5 | D51: 34612 | E51: 34654 | F51: 34618 | G51: 2 | H51: 5.74 | I51: Blondel père et fils | J51: 24, place Kléber | K51: Strasbourg | M51: 67000 | N51: France | O51: =TEXT(orders[[#This Row],[OrderDate]],"mmm") -> Oct | P51: =MONTH(orders[[#This Row],[OrderDate]]) -> 10 | Q51: =YEAR(orders[[#This Row],[OrderDate]]) -> 1994
A52: 10298 | B52: HUNGO | C52: 6 | D52: 34613 | E52: 34641 | F52: 34619 | G52: 2 | H52: 168.22 | I52: Hungry Owl All-Night Grocers | J52: 8 Johnstown Road | K52: Cork | L52: Co. Cork | N52: Ireland | O52: =TEXT(orders[[#This Row],[OrderDate]],"mmm") -> Oct | P52: =MONTH(orders[[#This Row],[OrderDate]]) -> 10 | Q52: =YEAR(orders[[#This Row],[OrderDate]]) -> 1994
A53: 10299 | B53: RICAR | C53: 4 | D53: 34614 | E53: 34642 | F53: 34621 | G53: 2 | H53: 29.76 | I53: Ricardo Adocicados | J53: Av. Copacabana, 267 | K53: Rio de Janeiro | L53: RJ | M53: 02389-890 | N53: Brazil | O53: =TEXT(orders[[#This Row],[OrderDate]],"mmm") -> Oct | P53: =MONTH(orders[[#This Row],[OrderDate]]) -> 10 | Q53: =YEAR(orders[[#This Row],[OrderDate]]) -> 1994
A54: 10300 | B54: MAGAA | C54: 2 | D54: 34617 | E54: 34645 | F54: 34626 | G54: 2 | H54: 17.68 | I54: Magazzini Alimentari Riuniti | J54: Via Ludovico il Moro 22 | K54: Bergamo | M54: 24100 | N54: Italy | O54: =TEXT(orders[[#This Row],[OrderDate]],"mmm") -> Oct | P54: =MONTH(orders[[#This Row],[OrderDate]]) -> 10 | Q54: =YEAR(orders[[#This Row],[OrderDate]]) -> 1994
A55: 10301 | B55: WANDK | C55: 8 | D55: 34617 | E55: 34645 | F55: 34625 | G55: 2 | H55: 45.08 | I55: Die Wandernde Kuh | J55: Adenauerallee 900 | K55: Stuttgart | M55: 70563 | N55: Germany | O55: =TEXT(orders[[#This Row],[OrderDate]],"mmm") -> Oct | P55: =MONTH(orders[[#This Row],[OrderDate]]) -> 10 | Q55: =YEAR(orders[[#This Row],[OrderDate]]) -> 1994
A56: 10302 | B56: SUPRD | C56: 4 | D56: 34618 | E56: 34646 | F56: 34647 | G56: 2 | H56: 6.27 | I56: Suprêmes délices | J56: Boulevard Tirou, 255 | K56: Charleroi | M56: B-6000 | N56: Belgium | O56: =TEXT(orders[[#This Row],[OrderDate]],"mmm") -> Oct | P56: =MONTH(orders[[#This Row],[OrderDate]]) -> 10 | Q56: =YEAR(orders[[#This Row],[OrderDate]]) -> 1994
A57: 10303 | B57: GODOS | C57: 7 | D57: 34619 | E57: 34647 | F57: 34626 | G57: 2 | H57: 107.83 | I57: Godos Cocina Típica | J57: C/ Romero, 33 | K57: Sevilla | M57: 41101 | N57: Spain | O57: =TEXT(orders[[#This Row],[OrderDate]],"mmm") -> Oct | P57: =MONTH(orders[[#This Row],[OrderDate]]) -> 10 | Q57: =YEAR(orders[[#This Row],[OrderDate]]) -> 1994
A58: 10304 | B58: TORTU | C58: 1 | D58: 34620 | E58: 34648 | F58: 34625 | G58: 2 | H58: 63.79 | I58: Tortuga Restaurante | J58: Avda. Azteca 123 | K58: México D.F. | M58: 05033 | N58: Mexico | O58: =TEXT(orders[[#This Row],[OrderDate]],"mmm") -> Oct | P58: =MONTH(orders[[#This Row],[OrderDate]]) -> 10 | Q58: =YEAR(orders[[#This Row],[OrderDate]]) -> 1994
A59: 10305 | B59: OLDWO | C59: 8 | D59: 34621 | E59: 34649 | F59: 34647 | G59: 3 | H59: 257.62 | I59: Old World Delicatessen | J59: 2743 Bering St. | K59: Anchorage | L59: AK | M59: 99508 | N59: USA | O59: =TEXT(orders[[#This Row],[OrderDate]],"mmm") -> Oct | P59: =MONTH(orders[[#This Row],[OrderDate]]) -> 10 | Q59: =YEAR(orders[[#This Row],[OrderDate]]) -> 1994
A60: 10306 | B60: ROMEY | C60: 1 | D60: 34624 | E60: 34652 | F60: 34631 | G60: 3 | H60: 7.56 | I60: Romero y tomillo | J60: Gran Vía, 1 | K60: Madrid | M60: 28001 | N60: Spain | O60: =TEXT(orders[[#This Row],[OrderDate]],"mmm") -> Oct | P60: =MONTH(orders[[#This Row],[OrderDate]]) -> 10 | Q60: =YEAR(orders[[#This Row],[OrderDate]]) -> 1994
A61: 10307 | B61: LONEP | C61: 2 | D61: 34625 | E61: 34653 | F61: 34633 | G61: 2 | H61: 0.56 | I61: Lonesome Pine Restaurant | J61: 89 Chiaroscuro Rd. | K61: Portland | L61: OR | M61: 97219 | N61: USA | O61: =TEXT(orders[[#This Row],[OrderDate]],"mmm") -> Oct | P61: =MONTH(orders[[#This Row],[OrderDate]]) -> 10 | Q61: =YEAR(orders[[#This Row],[OrderDate]]) -> 1994
A62: 10308 | B62: ANATR | C62: 7 | D62: 34626 | E62: 34654 | F62: 34632 | G62: 3 | H62: 1.61 | I62: Ana Trujillo Emparedados y helados | J62: Avda. de la Constitución 2222 | K62: México D.F. | M62: 05021 | N62: Mexico | O62: =TEXT(orders[[#This Row],[OrderDate]],"mmm") -> Oct | P62: =MONTH(orders[[#This Row],[OrderDate]]) -> 10 | Q62: =YEAR(orders[[#This Row],[OrderDate]]) -> 1994
A63: 10309 | B63: HUNGO | C63: 3 | D63: 34627 | E63: 34655 | F63: 34661 | G63: 1 | H63: 47.3 | I63: Hungry Owl All-Night Grocers | J63: 8 Johnstown Road | K63: Cork | L63: Co. Cork | N63: Ireland | O63: =TEXT(orders[[#This Row],[OrderDate]],"mmm") -> Oct | P63: =MONTH(orders[[#This Row],[OrderDate]]) -> 10 | Q63: =YEAR(orders[[#This Row],[OrderDate]]) -> 1994
A64: 10310 | B64: THEBI | C64: 8 | D64: 34628 | E64: 34656 | F64: 34635 | G64: 2 | H64: 17.52 | I64: The Big Cheese | J64: 89 Jefferson Way Suite 2 | K64: Portland | L64: OR | M64: 97201 | N64: USA | O64: =TEXT(orders[[#This Row],[OrderDate]],"mmm") -> Oct | P64: =MONTH(orders[[#This Row],[OrderDate]]) -> 10 | Q64: =YEAR(orders[[#This Row],[OrderDate]]) -> 1994
A65: 10311 | B65: DUMON | C65: 1 | D65: 34628 | E65: 34642 | F65: 34634 | G65: 3 | H65: 24.69 | I65: Du monde entier | J65: 67, rue des Cinquante Otages | K65: Nantes | M65: 44000 | N65: France | O65: =TEXT(orders[[#This Row],[OrderDate]],"mmm") -> Oct | P65: =MONTH(orders[[#This Row],[OrderDate]]) -> 10 | Q65: =YEAR(orders[[#This Row],[OrderDate]]) -> 1994
A66: 10312 | B66: WANDK | C66: 2 | D66: 34631 | E66: 34659 | F66: 34641 | G66: 2 | H66: 40.26 | I66: Die Wandernde Kuh | J66: Adenauerallee 900 | K66: Stuttgart | M66: 70563 | N66: Germany | O66: =TEXT(orders[[#This Row],[OrderDate]],"mmm") -> Oct | P66: =MONTH(orders[[#This Row],[OrderDate]]) -> 10 | Q66: =YEAR(orders[[#This Row],[OrderDate]]) -> 1994
A67: 10313 | B67: QUICK | C67: 2 | D67: 34632 | E67: 34660 | F67: 34642 | G67: 2 | H67: 1.96 | I67: QUICK-Stop | J67: Taucherstraße 10 | K67: Cunewalde | M67: 01307 | N67: Germany | O67: =TEXT(orders[[#This Row],[OrderDate]],"mmm") -> Oct | P67: =MONTH(orders[[#This Row],[OrderDate]]) -> 10 | Q67: =YEAR(orders[[#This Row],[OrderDate]]) -> 1994
A68: 10314 | B68: RATTC | C68: 1 | D68: 34633 | E68: 34661 | F68: 34642 | G68: 2 | H68: 74.16 | I68: Rattlesnake Canyon Grocery | J68: 2817 Milton Dr. | K68: Albuquerque | L68: NM | M68: 87110 | N68: USA | O68: =TEXT(orders[[#This Row],[OrderDate]],"mmm") -> Oct | P68: =MONTH(orders[[#This Row],[OrderDate]]) -> 10 | Q68: =YEAR(orders[[#This Row],[OrderDate]]) -> 1994
A69: 10315 | B69: ISLAT | C69: 4 | D69: 34634 | E69: 34662 | F69: 34641 | G69: 2 | H69: 41.76 | I69: Island Trading | J69: Garden House Crowther Way | K69: Cowes | L69: Isle of Wight | M69: PO31 7PJ | N69: UK | O69: =TEXT(orders[[#This Row],[OrderDate]],"mmm") -> Oct | P69: =MONTH(orders[[#This Row],[OrderDate]]) -> 10 | Q69: =YEAR(orders[[#This Row],[OrderDate]]) -> 1994
A70: 10316 | B70: RATTC | C70: 1 | D70: 34635 | E70: 34663 | F70: 34646 | G70: 3 | H70: 150.15 | I70: Rattlesnake Canyon Grocery | J70: 2817 Milton Dr. | K70: Albuquerque | L70: NM | M70: 87110 | N70: USA | O70: =TEXT(orders[[#This Row],[OrderDate]],"mmm") -> Oct | P70: =MONTH(orders[[#This Row],[OrderDate]]) -> 10 | Q70: =YEAR(orders[[#This Row],[OrderDate]]) -> 1994
A71: 10317 | B71: LONEP | C71: 6 | D71: 34638 | E71: 34666 | F71: 34648 | G71: 1 | H71: 12.69 | I71: Lonesome Pine Restaurant | J71: 89 Chiaroscuro Rd. | K71: Portland | L71: OR | M71: 97219 | N71: USA | O71: =TEXT(orders[[#This Row],[OrderDate]],"mmm") -> Oct | P71: =MONTH(orders[[#This Row],[OrderDate]]) -> 10 | Q71: =YEAR(orders[[#This Row],[OrderDate]]) -> 1994
A72: 10318 | B72: ISLAT | C72: 8 | D72: 34639 | E72: 34667 | F72: 34642 | G72: 2 | H72: 4.73 | I72: Island Trading | J72: Garden House Crowther Way | K72: Cowes | L72: Isle of Wight | M72: PO31 7PJ | N72: UK | O72: =TEXT(orders[[#This Row],[OrderDate]],"mmm") -> Nov | P72: =MONTH(orders[[#This Row],[OrderDate]]) -> 11 | Q72: =YEAR(orders[[#This Row],[OrderDate]]) -> 1994
A73: 10319 | B73: TORTU | C73: 7 | D73: 34640 | E73: 34668 | F73: 34649 | G73: 3 | H73: 64.5 | I73: Tortuga Restaurante | J73: Avda. Azteca 123 | K73: México D.F. | M73: 05033 | N73: Mexico | O73: =TEXT(orders[[#This Row],[OrderDate]],"mmm") -> Nov | P73: =MONTH(orders[[#This Row],[OrderDate]]) -> 11 | Q73: =YEAR(orders[[#This Row],[OrderDate]]) -> 1994
A74: 10320 | B74: WARTH | C74: 5 | D74: 34641 | E74: 34655 | F74: 34656 | G74: 3 | H74: 34.57 | I74: Wartian Herkku | J74: Torikatu 38 | K74: Oulu | M74: 90110 | N74: Finland | O74: =TEXT(orders[[#This Row],[OrderDate]],"mmm") -> Nov | P74: =MONTH(orders[[#This Row],[OrderDate]]) -> 11 | Q74: =YEAR(orders[[#This Row],[OrderDate]]) -> 1994
A75: 10321 | B75: ISLAT | C75: 3 | D75: 34641 | E75: 34669 | F75: 34649 | G75: 2 | H75: 3.43 | I75: Island Trading | J75: Garden House Crowther Way | K75: Cowes | L75: Isle of Wight | M75: PO31 7PJ | N75: UK | O75: =TEXT(orders[[#This Row],[OrderDate]],"mmm") -> Nov | P75: =MONTH(orders[[#This Row],[OrderDate]]) -> 11 | Q75: =YEAR(orders[[#This Row],[OrderDate]]) -> 1994
A76: 10322 | B76: PERIC | C76: 7 | D76: 34642 | E76: 34670 | F76: 34661 | G76: 3 | H76: 0.4 | I76: Pericles Comidas clásicas | J76: Calle Dr. Jorge Cash 321 | K76: México D.F. | M76: 05033 | N76: Mexico | O76: =TEXT(orders[[#This Row],[OrderDate]],"mmm") -> Nov | P76: =MONTH(orders[[#This Row],[OrderDate]]) -> 11 | Q76: =YEAR(orders[[#This Row],[OrderDate]]) -> 1994
A77: 10323 | B77: KOENE | C77: 4 | D77: 34645 | E77: 34673 | F77: 34652 | G77: 1 | H77: 4.88 | I77: Königlich Essen | J77: Maubelstr. 90 | K77: Brandenburg | M77: 14776 | N77: Germany | O77: =TEXT(orders[[#This Row],[OrderDate]],"mmm") -> Nov | P77: =MONTH(orders[[#This Row],[OrderDate]]) -> 11 | Q77: =YEAR(orders[[#This Row],[OrderDate]]) -> 1994
A78: 10324 | B78: SAVEA | C78: 9 | D78: 34646 | E78: 34674 | F78: 34648 | G78: 1 | H78: 214.27 | I78: Save-a-lot Markets | J78: 187 Suffolk Ln. | K78: Boise | L78: ID | M78: 83720 | N78: USA | O78: =TEXT(orders[[#This Row],[OrderDate]],"mmm") -> Nov | P78: =MONTH(orders[[#This Row],[OrderDate]]) -> 11 | Q78: =YEAR(orders[[#This Row],[OrderDate]]) -> 1994
A79: 10325 | B79: KOENE | C79: 1 | D79: 34647 | E79: 34661 | F79: 34652 | G79: 3 | H79: 64.86 | I79: Königlich Essen | J79: Maubelstr. 90 | K79: Brandenburg | M79: 14776 | N79: Germany | O79: =TEXT(orders[[#This Row],[OrderDate]],"mmm") -> Nov | P79: =MONTH(orders[[#This Row],[OrderDate]]) -> 11 | Q79: =YEAR(orders[[#This Row],[OrderDate]]) -> 1994
A80: 10326 | B80: BOLID | C80: 4 | D80: 34648 | E80: 34676 | F80: 34652 | G80: 2 | H80: 77.92 | I80: Bólido Comidas preparadas | J80: C/ Araquil, 67 | K80: Madrid | M80: 28023 | N80: Spain | O80: =TEXT(orders[[#This Row],[OrderDate]],"mmm") -> Nov | P80: =MONTH(orders[[#This Row],[OrderDate]]) -> 11 | Q80: =YEAR(orders[[#This Row],[OrderDate]]) -> 1994
A81: 10327 | B81: FOLKO | C81: 2 | D81: 34649 | E81: 34677 | F81: 34652 | G81: 1 | H81: 63.36 | I81: Folk och fä HB | J81: Åkergatan 24 | K81: Bräcke | M81: S-844 67 | N81: Sweden | O81: =TEXT(orders[[#This Row],[OrderDate]],"mmm") -> Nov | P81: =MONTH(orders[[#This Row],[OrderDate]]) -> 11 | Q81: =YEAR(orders[[#This Row],[OrderDate]]) -> 1994
A82: 10328 | B82: FURIB | C82: 4 | D82: 34652 | E82: 34680 | F82: 34655 | G82: 3 | H82: 87.03 | I82: Furia Bacalhau e Frutos do Mar | J82: Jardim das rosas n. 32 | K82: Lisboa | M82: 1675 | N82: Portugal | O82: =TEXT(orders[[#This Row],[OrderDate]],"mmm") -> Nov | P82: =MONTH(orders[[#This Row],[OrderDate]]) -> 11 | Q82: =YEAR(orders[[#This Row],[OrderDate]]) -> 1994
A83: 10329 | B83: SPLIR | C83: 4 | D83: 34653 | E83: 34695 | F83: 34661 | G83: 2 | H83: 191.67 | I83: Split Rail Beer & Ale | J83: P.O. Box 555 | K83: Lander | L83: WY | M83: 82520 | N83: USA | O83: =TEXT(orders[[#This Row],[OrderDate]],"mmm") -> Nov | P83: =MONTH(orders[[#This Row],[OrderDate]]) -> 11 | Q83: =YEAR(orders[[#This Row],[OrderDate]]) -> 1994
A84: 10330 | B84: LILAS | C84: 3 | D84: 34654 | E84: 34682 | F84: 34666 | G84: 1 | H84: 12.75 | I84: LILA-Supermercado | J84: Carrera 52 con Ave. Bolívar #65-98 Llano Largo | K84: Barquisimeto | L84: Lara | M84: 3508 | N84: Venezuela | O84: =TEXT(orders[[#This Row],[OrderDate]],"mmm") -> Nov | P84: =MONTH(orders[[#This Row],[OrderDate]]) -> 11 | Q84: =YEAR(orders[[#This Row],[OrderDate]]) -> 1994
A85: 10331 | B85: BONAP | C85: 9 | D85: 34654 | E85: 34696 | F85: 34659 | G85: 1 | H85: 10.19 | I85: Bon app' | J85: 12, rue des Bouchers | K85: Marseille | M85: 13008 | N85: France | O85: =TEXT(orders[[#This Row],[OrderDate]],"mmm") -> Nov | P85: =MONTH(orders[[#This Row],[OrderDate]]) -> 11 | Q85: =YEAR(orders[[#This Row],[OrderDate]]) -> 1994
A86: 10332 | B86: MEREP | C86: 3 | D86: 34655 | E86: 34697 | F86: 34659 | G86: 2 | H86: 52.84 | I86: Mère Paillarde | J86: 43 rue St. Laurent | K86: Montréal | L86: Québec | M86: H1J 1C3 | N86: Canada | O86: =TEXT(orders[[#This Row],[OrderDate]],"mmm") -> Nov | P86: =MONTH(orders[[#This Row],[OrderDate]]) -> 11 | Q86: =YEAR(orders[[#This Row],[OrderDate]]) -> 1994
A87: 10333 | B87: WARTH | C87: 5 | D87: 34656 | E87: 34684 | F87: 34663 | G87: 3 | H87: 0.59 | I87: Wartian Herkku | J87: Torikatu 38 | K87: Oulu | M87: 90110 | N87: Finland | O87: =TEXT(orders[[#This Row],[OrderDate]],"mmm") -> Nov | P87: =MONTH(orders[[#This Row],[OrderDate]]) -> 11 | Q87: =YEAR(orders[[#This Row],[OrderDate]]) -> 1994
A88: 10334 | B88: VICTE | C88: 8 | D88: 34659 | E88: 34687 | F88: 34666 | G88: 2 | H88: 8.56 | I88: Victuailles en stock | J88: 2, rue du Commerce | K88: Lyon | M88: 69004 | N88: France | O88: =TEXT(orders[[#This Row],[OrderDate]],"mmm") -> Nov | P88: =MONTH(orders[[#This Row],[OrderDate]]) -> 11 | Q88: =YEAR(orders[[#This Row],[OrderDate]]) -> 1994
A89: 10335 | B89: HUNGO | C89: 7 | D89: 34660 | E89: 34688 | F89: 34662 | G89: 2 | H89: 42.11 | I89: Hungry Owl All-Night Grocers | J89: 8 Johnstown Road | K89: Cork | L89: Co. Cork | N89: Ireland | O89: =TEXT(orders[[#This Row],[OrderDate]],"mmm") -> Nov | P89: =MONTH(orders[[#This Row],[OrderDate]]) -> 11 | Q89: =YEAR(orders[[#This Row],[OrderDate]]) -> 1994
A90: 10336 | B90: PRINI | C90: 7 | D90: 34661 | E90: 34689 | F90: 34663 | G90: 2 | H90: 15.51 | I90: Princesa Isabel Vinhos | J90: Estrada da saúde n. 58 | K90: Lisboa | M90: 1756 | N90: Portugal | O90: =TEXT(orders[[#This Row],[OrderDate]],"mmm") -> Nov | P90: =MONTH(orders[[#This Row],[OrderDate]]) -> 11 | Q90: =YEAR(orders[[#This Row],[OrderDate]]) -> 1994
A91: 10337 | B91: FRANK | C91: 4 | D91: 34662 | E91: 34690 | F91: 34667 | G91: 3 | H91: 108.26 | I91: Frankenversand | J91: Berliner Platz 43 | K91: München | M91: 80805 | N91: Germany | O91: =TEXT(orders[[#This Row],[OrderDate]],"mmm") -> Nov | P91: =MONTH(orders[[#This Row],[OrderDate]]) -> 11 | Q91: =YEAR(orders[[#This Row],[OrderDate]]) -> 1994
A92: 10338 | B92: OLDWO | C92: 4 | D92: 34663 | E92: 34691 | F92: 34667 | G92: 3 | H92: 84.21 | I92: Old World Delicatessen | J92: 2743 Bering St. | K92: Anchorage | L92: AK | M92: 99508 | N92: USA | O92: =TEXT(orders[[#This Row],[OrderDate]],"mmm") -> Nov | P92: =MONTH(orders[[#This Row],[OrderDate]]) -> 11 | Q92: =YEAR(orders[[#This Row],[OrderDate]]) -> 1994
A93: 10339 | B93: MEREP | C93: 2 | D93: 34666 | E93: 34694 | F93: 34673 | G93: 2 | H93: 15.66 | I93: Mère Paillarde | J93: 43 rue St. Laurent | K93: Montréal | L93: Québec | M93: H1J 1C3 | N93: Canada | O93: =TEXT(orders[[#This Row],[OrderDate]],"mmm") -> Nov | P93: =MONTH(orders[[#This Row],[OrderDate]]) -> 11 | Q93: =YEAR(orders[[#This Row],[OrderDate]]) -> 1994
A94: 10340 | B94: BONAP | C94: 1 | D94: 34667 | E94: 34695 | F94: 34677 | G94: 3 | H94: 166.31 | I94: Bon app' | J94: 12, rue des Bouchers | K94: Marseille | M94: 13008 | N94: France | O94: =TEXT(orders[[#This Row],[OrderDate]],"mmm") -> Nov | P94: =MONTH(orders[[#This Row],[OrderDate]]) -> 11 | Q94: =YEAR(orders[[#This Row],[OrderDate]]) -> 1994
A95: 10341 | B95: SIMOB | C95: 7 | D95: 34667 | E95: 34695 | F95: 34674 | G95: 3 | H95: 26.78 | I95: Simons bistro | J95: Vinbæltet 34 | K95: København | M95: 1734 | N95: Denmark | O95: =TEXT(orders[[#This Row],[OrderDate]],"mmm") -> Nov | P95: =MONTH(orders[[#This Row],[OrderDate]]) -> 11 | Q95: =YEAR(orders[[#This Row],[OrderDate]]) -> 1994
A96: 10342 | B96: FRANK | C96: 4 | D96: 34668 | E96: 34682 | F96: 34673 | G96: 2 | H96: 54.83 | I96: Frankenversand | J96: Berliner Platz 43 | K96: München | M96: 80805 | N96: Germany | O96: =TEXT(orders[[#This Row],[OrderDate]],"mmm") -> Nov | P96: =MONTH(orders[[#This Row],[OrderDate]]) -> 11 | Q96: =YEAR(orders[[#This Row],[OrderDate]]) -> 1994
A97: 10343 | B97: LEHMS | C97: 4 | D97: 34669 | E97: 34697 | F97: 34675 | G97: 1 | H97: 110.37 | I97: Lehmanns Marktstand | J97: Magazinweg 7 | K97: Frankfurt a.M. | M97: 60528 | N97: Germany | O97: =TEXT(orders[[#This Row],[OrderDate]],"mmm") -> Dec | P97: =MONTH(orders[[#This Row],[OrderDate]]) -> 12 | Q97: =YEAR(orders[[#This Row],[OrderDate]]) -> 1994
A98: 10344 | B98: WHITC | C98: 4 | D98: 34670 | E98: 34698 | F98: 34674 | G98: 2 | H98: 23.29 | I98: White Clover Markets | J98: 1029 - 12th Ave. S. | K98: Seattle | L98: WA | M98: 98124 | N98: USA | O98: =TEXT(orders[[#This Row],[OrderDate]],"mmm") -> Dec | P98: =MONTH(orders[[#This Row],[OrderDate]]) -> 12 | Q98: =YEAR(orders[[#This Row],[OrderDate]]) -> 1994
A99: 10345 | B99: QUICK | C99: 2 | D99: 34673 | E99: 34701 | F99: 34680 | G99: 2 | H99: 249.06 | I99: QUICK-Stop | J99: Taucherstraße 10 | K99: Cunewalde | M99: 01307 | N99: Germany | O99: =TEXT(orders[[#This Row],[OrderDate]],"mmm") -> Dec | P99: =MONTH(orders[[#This Row],[OrderDate]]) -> 12 | Q99: =YEAR(orders[[#This Row],[OrderDate]]) -> 1994
A100: 10346 | B100: RATTC | C100: 3 | D100: 34674 | E100: 34716 | F100: 34677 | G100: 3 | H100: 142.08 | I100: Rattlesnake Canyon Grocery | J100: 2817 Milton Dr. | K100: Albuquerque | L100: NM | M100: 87110 | N100: USA | O100: =TEXT(orders[[#This Row],[OrderDate]],"mmm") -> Dec | P100: =MONTH(orders[[#This Row],[OrderDate]]) -> 12 | Q100: =YEAR(orders[[#This Row],[OrderDate]]) -> 1994
...

Sheet order details
A1: OrderID | B1: ProductID | C1: UnitPrice | D1: Quantity | E1: Discount | F1: Total_sales | G1: CustomerID | H1: ShipCountry | I1: ShipCity | J1: CategoryID | K1: Category Name | L1: month | M1: month number | N1: year | P1: ShipCity | Q1: ShipCountry | R1: Total_sales
A2: 10248 | B2: 11 | C2: 14 | D2: 12 | E2: 0 | F2: =order_details[[#This Row],[UnitPrice]]*order_details[[#This Row],[Quantity]]*(1-order_details[[#This Row],[Discount]]) -> 168 | G2: =_xlfn.XLOOKUP(order_details[[#This Row],[OrderID]],orders[OrderID],orders[CustomerID]) -> VINET | H2: =_xlfn.XLOOKUP(order_details[[#This Row],[CustomerID]],orders[CustomerID],orders[ShipCountry]) -> France | I2: =_xlfn.XLOOKUP(order_details[[#This Row],[CustomerID]],orders[CustomerID],orders[ShipCity]) -> Reims | J2: =_xlfn.XLOOKUP(order_details[[#This Row],[ProductID]],products[ProductID],products[CategoryID]) -> 4 | K2: =_xlfn.XLOOKUP(order_details[[#This Row],[CategoryID]],categories[CategoryID],categories[CategoryName]) -> Dairy Products | L2: =_xlfn.XLOOKUP(order_details[[#This Row],[OrderID]],orders[OrderID],orders[month]) -> Aug | M2: =_xlfn.XLOOKUP(order_details[[#This Row],[OrderID]],orders[OrderID],orders[month number]) -> 8 | N2: =_xlfn.XLOOKUP(order_details[[#This Row],[OrderID]],orders[OrderID],orders[year]) -> 1994 | P2: =_xlfn.XLOOKUP(order_details[[#This Row],[CustomerID]],orders[CustomerID],orders[ShipCity]) -> Reims | Q2: =_xlfn.XLOOKUP(order_details[[#This Row],[CustomerID]],orders[CustomerID],orders[ShipCountry]) -> France | R2: =order_details[[#This Row],[UnitPrice]]*order_details[[#This Row],[Quantity]]*(1-order_details[[#This Row],[Discount]]) -> 168
A3: 10248 | B3: 42 | C3: 9.8 | D3: 10 | E3: 0 | F3: =order_details[[#This Row],[UnitPrice]]*order_details[[#This Row],[Quantity]]*(1-order_details[[#This Row],[Discount]]) -> 98 | G3: =_xlfn.XLOOKUP(order_details[[#This Row],[OrderID]],orders[OrderID],orders[CustomerID]) -> VINET | H3: =_xlfn.XLOOKUP(order_details[[#This Row],[CustomerID]],orders[CustomerID],orders[ShipCountry]) -> France | I3: =_xlfn.XLOOKUP(order_details[[#This Row],[CustomerID]],orders[CustomerID],orders[ShipCity]) -> Reims | J3: =_xlfn.XLOOKUP(order_details[[#This Row],[ProductID]],products[ProductID],products[CategoryID]) -> 5 | K3: =_xlfn.XLOOKUP(order_details[[#This Row],[CategoryID]],categories[CategoryID],categories[CategoryName]) -> Grains/Cereals | L3: =_xlfn.XLOOKUP(order_details[[#This Row],[OrderID]],orders[OrderID],orders[month]) -> Aug | M3: =_xlfn.XLOOKUP(order_details[[#This Row],[OrderID]],orders[OrderID],orders[month number]) -> 8 | N3: =_xlfn.XLOOKUP(order_details[[#This Row],[OrderID]],orders[OrderID],orders[year]) -> 1994 | P3: =_xlfn.XLOOKUP(order_details[[#This Row],[CustomerID]],orders[CustomerID],orders[ShipCity]) -> Reims | Q3: =_xlfn.XLOOKUP(order_details[[#This Row],[CustomerID]],orders[CustomerID],orders[ShipCountry]) -> France | R3: =order_details[[#This Row],[UnitPrice]]*order_details[[#This Row],[Quantity]]*(1-order_details[[#This Row],[Discount]]) -> 98
A4: 10248 | B4: 72 | C4: 34.8 | D4: 5 | E4: 0 | F4: =order_details[[#This Row],[UnitPrice]]*order_details[[#This Row],[Quantity]]*(1-order_details[[#This Row],[Discount]]) -> 174 | G4: =_xlfn.XLOOKUP(order_details[[#This Row],[OrderID]],orders[OrderID],orders[CustomerID]) -> VINET | H4: =_xlfn.XLOOKUP(order_details[[#This Row],[CustomerID]],orders[CustomerID],orders[ShipCountry]) -> France | I4: =_xlfn.XLOOKUP(order_details[[#This Row],[CustomerID]],orders[CustomerID],orders[ShipCity]) -> Reims | J4: =_xlfn.XLOOKUP(order_details[[#This Row],[ProductID]],products[ProductID],products[CategoryID]) -> 4 | K4: =_xlfn.XLOOKUP(order_details[[#This Row],[CategoryID]],categories[CategoryID],categories[CategoryName]) -> Dairy Products | L4: =_xlfn.XLOOKUP(order_details[[#This Row],[OrderID]],orders[OrderID],orders[month]) -> Aug | M4: =_xlfn.XLOOKUP(order_details[[#This Row],[OrderID]],orders[OrderID],orders[month number]) -> 8 | N4: =_xlfn.XLOOKUP(order_details[[#This Row],[OrderID]],orders[OrderID],orders[year]) -> 1994 | P4: =_xlfn.XLOOKUP(order_details[[#This Row],[CustomerID]],orders[CustomerID],orders[ShipCity]) -> Reims | Q4: =_xlfn.XLOOKUP(order_details[[#This Row],[CustomerID]],orders[CustomerID],orders[ShipCountry]) -> France | R4: =order_details[[#This Row],[UnitPrice]]*order_details[[#This Row],[Quantity]]*(1-order_details[[#This Row],[Discount]]) -> 174
A5: 10249 | B5: 14 | C5: 18.6 | D5: 9 | E5: 0 | F5: =order_details[[#This Row],[UnitPrice]]*order_details[[#This Row],[Quantity]]*(1-order_details[[#This Row],[Discount]]) -> 167.4 | G5: =_xlfn.XLOOKUP(order_details[[#This Row],[OrderID]],orders[OrderID],orders[CustomerID]) -> TOMSP | H5: =_xlfn.XLOOKUP(order_details[[#This Row],[CustomerID]],orders[CustomerID],orders[ShipCountry]) -> Germany | I5: =_xlfn.XLOOKUP(order_details[[#This Row],[CustomerID]],orders[CustomerID],orders[ShipCity]) -> Münster | J5: =_xlfn.XLOOKUP(order_details[[#This Row],[ProductID]],products[ProductID],products[CategoryID]) -> 7 | K5: =_xlfn.XLOOKUP(order_details[[#This Row],[CategoryID]],categories[CategoryID],categories[CategoryName]) -> Produce | L5: =_xlfn.XLOOKUP(order_details[[#This Row],[OrderID]],orders[OrderID],orders[month]) -> Aug | M5: =_xlfn.XLOOKUP(order_details[[#This Row],[OrderID]],orders[OrderID],orders[month number]) -> 8 | N5: =_xlfn.XLOOKUP(order_details[[#This Row],[OrderID]],orders[OrderID],orders[year]) -> 1994 | P5: =_xlfn.XLOOKUP(order_details[[#This Row],[CustomerID]],orders[CustomerID],orders[ShipCity]) -> Münster | Q5: =_xlfn.XLOOKUP(order_details[[#This Row],[CustomerID]],orders[CustomerID],orders[ShipCountry]) -> Germany | R5: =order_details[[#This Row],[UnitPrice]]*order_details[[#This Row],[Quantity]]*(1-order_details[[#This Row],[Discount]]) -> 167.4
A6: 10249 | B6: 51 | C6: 42.4 | D6: 40 | E6: 0 | F6: =order_details[[#This Row],[UnitPrice]]*order_details[[#This Row],[Quantity]]*(1-order_details[[#This Row],[Discount]]) -> 1696 | G6: =_xlfn.XLOOKUP(order_details[[#This Row],[OrderID]],orders[OrderID],orders[CustomerID]) -> TOMSP | H6: =_xlfn.XLOOKUP(order_details[[#This Row],[CustomerID]],orders[CustomerID],orders[ShipCountry]) -> Germany | I6: =_xlfn.XLOOKUP(order_details[[#This Row],[CustomerID]],orders[CustomerID],orders[ShipCity]) -> Münster | J6: =_xlfn.XLOOKUP(order_details[[#This Row],[ProductID]],products[ProductID],products[CategoryID]) -> 7 | K6: =_xlfn.XLOOKUP(order_details[[#This Row],[CategoryID]],categories[CategoryID],categories[CategoryName]) -> Produce | L6: =_xlfn.XLOOKUP(order_details[[#This Row],[OrderID]],orders[OrderID],orders[month]) -> Aug | M6: =_xlfn.XLOOKUP(order_details[[#This Row],[OrderID]],orders[OrderID],orders[month number]) -> 8 | N6: =_xlfn.XLOOKUP(order_details[[#This Row],[OrderID]],orders[OrderID],orders[year]) -> 1994 | P6: =_xlfn.XLOOKUP(order_details[[#This Row],[CustomerID]],orders[CustomerID],orders[ShipCity]) -> Münster | Q6: =_xlfn.XLOOKUP(order_details[[#This Row],[CustomerID]],orders[CustomerID],orders[ShipCountry]) -> Germany | R6: =order_details[[#This Row],[UnitPrice]]*order_details[[#This Row],[Quantity]]*(1-order_details[[#This Row],[Discount]]) -> 1696
A7: 10250 | B7: 41 | C7: 7.7 | D7: 10 | E7: 0 | F7: =order_details[[#This Row],[UnitPrice]]*order_details[[#This Row],[Quantity]]*(1-order_details[[#This Row],[Discount]]) -> 77 | G7: =_xlfn.XLOOKUP(order_details[[#This Row],[OrderID]],orders[OrderID],orders[CustomerID]) -> HANAR | H7: =_xlfn.XLOOKUP(order_details[[#This Row],[CustomerID]],orders[CustomerID],orders[ShipCountry]) -> Brazil | I7: =_xlfn.XLOOKUP(order_details[[#This Row],[CustomerID]],orders[CustomerID],orders[ShipCity]) -> Rio de Janeiro | J7: =_xlfn.XLOOKUP(order_details[[#This Row],[ProductID]],products[ProductID],products[CategoryID]) -> 8 | K7: =_xlfn.XLOOKUP(order_details[[#This Row],[CategoryID]],categories[CategoryID],categories[CategoryName]) -> Seafood | L7: =_xlfn.XLOOKUP(order_details[[#This Row],[OrderID]],orders[OrderID],orders[month]) -> Aug | M7: =_xlfn.XLOOKUP(order_details[[#This Row],[OrderID]],orders[OrderID],orders[month number]) -> 8 | N7: =_xlfn.XLOOKUP(order_details[[#This Row],[OrderID]],orders[OrderID],orders[year]) -> 1994 | P7: =_xlfn.XLOOKUP(order_details[[#This Row],[CustomerID]],orders[CustomerID],orders[ShipCity]) -> Rio de Janeiro | Q7: =_xlfn.XLOOKUP(order_details[[#This Row],[CustomerID]],orders[CustomerID],orders[ShipCountry]) -> Brazil | R7: =order_details[[#This Row],[UnitPrice]]*order_details[[#This Row],[Quantity]]*(1-order_details[[#This Row],[Discount]]) -> 77
A8: 10250 | B8: 51 | C8: 42.4 | D8: 35 | E8: 0.15 | F8: =order_details[[#This Row],[UnitPrice]]*order_details[[#This Row],[Quantity]]*(1-order_details[[#This Row],[Discount]]) -> 1261.4 | G8: =_xlfn.XLOOKUP(order_details[[#This Row],[OrderID]],orders[OrderID],orders[CustomerID]) -> HANAR | H8: =_xlfn.XLOOKUP(order_details[[#This Row],[CustomerID]],orders[CustomerID],orders[ShipCountry]) -> Brazil | I8: =_xlfn.XLOOKUP(order_details[[#This Row],[CustomerID]],orders[CustomerID],orders[ShipCity]) -> Rio de Janeiro | J8: =_xlfn.XLOOKUP(order_details[[#This Row],[ProductID]],products[ProductID],products[CategoryID]) -> 7 | K8: =_xlfn.XLOOKUP(order_details[[#This Row],[CategoryID]],categories[CategoryID],categories[CategoryName]) -> Produce | L8: =_xlfn.XLOOKUP(order_details[[#This Row],[OrderID]],orders[OrderID],orders[month]) -> Aug | M8: =_xlfn.XLOOKUP(order_details[[#This Row],[OrderID]],orders[OrderID],orders[month number]) -> 8 | N8: =_xlfn.XLOOKUP(order_details[[#This Row],[OrderID]],orders[OrderID],orders[year]) -> 1994 | P8: =_xlfn.XLOOKUP(order_details[[#This Row],[CustomerID]],orders[CustomerID],orders[ShipCity]) -> Rio de Janeiro | Q8: =_xlfn.XLOOKUP(order_details[[#This Row],[CustomerID]],orders[CustomerID],orders[ShipCountry]) -> Brazil | R8: =order_details[[#This Row],[UnitPrice]]*order_details[[#This Row],[Quantity]]*(1-order_details[[#This Row],[Discount]]) -> 1261.4
A9: 10250 | B9: 65 | C9: 16.8 | D9: 15 | E9: 0.15 | F9: =order_details[[#This Row],[UnitPrice]]*order_details[[#This Row],[Quantity]]*(1-order_details[[#This Row],[Discount]]) -> 214.2 | G9: =_xlfn.XLOOKUP(order_details[[#This Row],[OrderID]],orders[OrderID],orders[CustomerID]) -> HANAR | H9: =_xlfn.XLOOKUP(order_details[[#This Row],[CustomerID]],orders[CustomerID],orders[ShipCountry]) -> Brazil | I9: =_xlfn.XLOOKUP(order_details[[#This Row],[CustomerID]],orders[CustomerID],orders[ShipCity]) -> Rio de Janeiro | J9: =_xlfn.XLOOKUP(order_details[[#This Row],[ProductID]],products[ProductID],products[CategoryID]) -> 2 | K9: =_xlfn.XLOOKUP(order_details[[#This Row],[CategoryID]],categories[CategoryID],categories[CategoryName]) -> Condiments | L9: =_xlfn.XLOOKUP(order_details[[#This Row],[OrderID]],orders[OrderID],orders[month]) -> Aug | M9: =_xlfn.XLOOKUP(order_details[[#This Row],[OrderID]],orders[OrderID],orders[month number]) -> 8 | N9: =_xlfn.XLOOKUP(order_details[[#This Row],[OrderID]],orders[OrderID],orders[year]) -> 1994 | P9: =_xlfn.XLOOKUP(order_details[[#This Row],[CustomerID]],orders[CustomerID],orders[ShipCity]) -> Rio de Janeiro | Q9: =_xlfn.XLOOKUP(order_details[[#This Row],[CustomerID]],orders[CustomerID],orders[ShipCountry]) -> Brazil | R9: =order_details[[#This Row],[UnitPrice]]*order_details[[#This Row],[Quantity]]*(1-order_details[[#This Row],[Discount]]) -> 214.2
A10: 10251 | B10: 22 | C10: 16.8 | D10: 6 | E10: 0.05 | F10: =order_details[[#This Row],[UnitPrice]]*order_details[[#This Row],[Quantity]]*(1-order_details[[#This Row],[Discount]]) -> 95.76 | G10: =_xlfn.XLOOKUP(order_details[[#This Row],[OrderID]],orders[OrderID],orders[CustomerID]) -> VICTE | H10: =_xlfn.XLOOKUP(order_details[[#This Row],[CustomerID]],orders[CustomerID],orders[ShipCountry]) -> France | I10: =_xlfn.XLOOKUP(order_details[[#This Row],[CustomerID]],orders[CustomerID],orders[ShipCity]) -> Lyon | J10: =_xlfn.XLOOKUP(order_details[[#This Row],[ProductID]],products[ProductID],products[CategoryID]) -> 5 | K10: =_xlfn.XLOOKUP(order_details[[#This Row],[CategoryID]],categories[CategoryID],categories[CategoryName]) -> Grains/Cereals | L10: =_xlfn.XLOOKUP(order_details[[#This Row],[OrderID]],orders[OrderID],orders[month]) -> Aug | M10: =_xlfn.XLOOKUP(order_details[[#This Row],[OrderID]],orders[OrderID],orders[month number]) -> 8 | N10: =_xlfn.XLOOKUP(order_details[[#This Row],[OrderID]],orders[OrderID],orders[year]) -> 1994 | P10: =_xlfn.XLOOKUP(order_details[[#This Row],[CustomerID]],orders[CustomerID],orders[ShipCity]) -> Lyon | Q10: =_xlfn.XLOOKUP(order_details[[#This Row],[CustomerID]],orders[CustomerID],orders[ShipCountry]) -> France | R10: =order_details[[#This Row],[UnitPrice]]*order_details[[#This Row],[Quantity]]*(1-order_details[[#This Row],[Discount]]) -> 95.76
A11: 10251 | B11: 57 | C11: 15.6 | D11: 15 | E11: 0.05 | F11: =order_details[[#This Row],[UnitPrice]]*order_details[[#This Row],[Quantity]]*(1-order_details[[#This Row],[Discount]]) -> 222.3 | G11: =_xlfn.XLOOKUP(order_details[[#This Row],[OrderID]],orders[OrderID],orders[CustomerID]) -> VICTE | H11: =_xlfn.XLOOKUP(order_details[[#This Row],[CustomerID]],orders[CustomerID],orders[ShipCountry]) -> France | I11: =_xlfn.XLOOKUP(order_details[[#This Row],[CustomerID]],orders[CustomerID],orders[ShipCity]) -> Lyon | J11: =_xlfn.XLOOKUP(order_details[[#This Row],[ProductID]],products[ProductID],products[CategoryID]) -> 5 | K11: =_xlfn.XLOOKUP(order_details[[#This Row],[CategoryID]],categories[CategoryID],categories[CategoryName]) -> Grains/Cereals | L11: =_xlfn.XLOOKUP(order_details[[#This Row],[OrderID]],orders[OrderID],orders[month]) -> Aug | M11: =_xlfn.XLOOKUP(order_details[[#This Row],[OrderID]],orders[OrderID],orders[month number]) -> 8 | N11: =_xlfn.XLOOKUP(order_details[[#This Row],[OrderID]],orders[OrderID],orders[year]) -> 1994 | P11: =_xlfn.XLOOKUP(order_details[[#This Row],[CustomerID]],orders[CustomerID],orders[ShipCity]) -> Lyon | Q11: =_xlfn.XLOOKUP(order_details[[#This Row],[CustomerID]],orders[CustomerID],orders[ShipCountry]) -> France | R11: =order_details[[#This Row],[UnitPrice]]*order_details[[#This Row],[Quantity]]*(1-order_details[[#This Row],[Discount]]) -> 222.3
A12: 10251 | B12: 65 | C12: 16.8 | D12: 20 | E12: 0 | F12: =order_details[[#This Row],[UnitPrice]]*order_details[[#This Row],[Quantity]]*(1-order_details[[#This Row],[Discount]]) -> 336 | G12: =_xlfn.XLOOKUP(order_details[[#This Row],[OrderID]],orders[OrderID],orders[CustomerID]) -> VICTE | H12: =_xlfn.XLOOKUP(order_details[[#This Row],[CustomerID]],orders[CustomerID],orders[ShipCountry]) -> France | I12: =_xlfn.XLOOKUP(order_details[[#This Row],[CustomerID]],orders[CustomerID],orders[ShipCity]) -> Lyon | J12: =_xlfn.XLOOKUP(order_details[[#This Row],[ProductID]],products[ProductID],products[CategoryID]) -> 2 | K12: =_xlfn.XLOOKUP(order_details[[#This Row],[CategoryID]],categories[CategoryID],categories[CategoryName]) -> Condiments | L12: =_xlfn.XLOOKUP(order_details[[#This Row],[OrderID]],orders[OrderID],orders[month]) -> Aug | M12: =_xlfn.XLOOKUP(order_details[[#This Row],[OrderID]],orders[OrderID],orders[month number]) -> 8 | N12: =_xlfn.XLOOKUP(order_details[[#This Row],[OrderID]],orders[OrderID],orders[year]) -> 1994 | P12: =_xlfn.XLOOKUP(order_details[[#This Row],[CustomerID]],orders[CustomerID],orders[ShipCity]) -> Lyon | Q12: =_xlfn.XLOOKUP(order_details[[#This Row],[CustomerID]],orders[CustomerID],orders[ShipCountry]) -> France | R12: =order_details[[#This Row],[UnitPrice]]*order_details[[#This Row],[Quantity]]*(1-order_details[[#This Row],[Discount]]) -> 336
A13: 10252 | B13: 20 | C13: 64.8 | D13: 40 | E13: 0.05 | F13: =order_details[[#This Row],[UnitPrice]]*order_details[[#This Row],[Quantity]]*(1-order_details[[#This Row],[Discount]]) -> 2462.4 | G13: =_xlfn.XLOOKUP(order_details[[#This Row],[OrderID]],orders[OrderID],orders[CustomerID]) -> SUPRD | H13: =_xlfn.XLOOKUP(order_details[[#This Row],[CustomerID]],orders[CustomerID],orders[ShipCountry]) -> Belgium | I13: =_xlfn.XLOOKUP(order_details[[#This Row],[CustomerID]],orders[CustomerID],orders[ShipCity]) -> Charleroi | J13: =_xlfn.XLOOKUP(order_details[[#This Row],[ProductID]],products[ProductID],products[CategoryID]) -> 3 | K13: =_xlfn.XLOOKUP(order_details[[#This Row],[CategoryID]],categories[CategoryID],categories[CategoryName]) -> Confections | L13: =_xlfn.XLOOKUP(order_details[[#This Row],[OrderID]],orders[OrderID],orders[month]) -> Aug | M13: =_xlfn.XLOOKUP(order_details[[#This Row],[OrderID]],orders[OrderID],orders[month number]) -> 8 | N13: =_xlfn.XLOOKUP(order_details[[#This Row],[OrderID]],orders[OrderID],orders[year]) -> 1994 | P13: =_xlfn.XLOOKUP(order_details[[#This Row],[CustomerID]],orders[CustomerID],orders[ShipCity]) -> Charleroi | Q13: =_xlfn.XLOOKUP(order_details[[#This Row],[CustomerID]],orders[CustomerID],orders[ShipCountry]) -> Belgium | R13: =order_details[[#This Row],[UnitPrice]]*order_details[[#This Row],[Quantity]]*(1-order_details[[#This Row],[Discount]]) -> 2462.4
... A2156: 11077 | B2156: 77 | C2156: 13 | D2156: 2 | E2156: 0 | F2156: =order_details[[#This Row],[UnitPrice]]*order_details[[#This Row],[Quantity]]*(1-order_details[[#This Row],[Discount]]) -> 26 | G2156: =_xlfn.XLOOKUP(order_details[[#This Row],[OrderID]],orders[OrderID],orders[CustomerID]) -> RATTC | H2156: =_xlfn.XLOOKUP(order_details[[#This Row],[CustomerID]],orders[CustomerID],orders[ShipCountry]) -> USA | I2156: =_xlfn.XLOOKUP(order_details[[#This Row],[CustomerID]],orders[CustomerID],orders[ShipCity]) -> Albuquerque | J2156: =_xlfn.XLOOKUP(order_details[[#This Row],[ProductID]],products[ProductID],products[CategoryID]) -> 2 | K2156: =_xlfn.XLOOKUP(order_details[[#This Row],[CategoryID]],categories[CategoryID],categories[CategoryName]) -> Condiments | L2156: =_xlfn.XLOOKUP(order_details[[#This Row],[OrderID]],orders[OrderID],orders[month]) -> Jun | M2156: =_xlfn.XLOOKUP(order_details[[#This Row],[OrderID]],orders[OrderID],orders[month number]) -> 6 | N2156: =_xlfn.XLOOKUP(order_details[[#This Row],[OrderID]],orders[OrderID],orders[year]) -> 1996 | P2156: =_xlfn.XLOOKUP(order_details[[#This Row],[CustomerID]],orders[CustomerID],orders[ShipCity]) -> Albuquerque | Q2156: =_xlfn.XLOOKUP(order_details[[#This Row],[CustomerID]],orders[CustomerID],orders[ShipCountry]) -> USA | R2156: =order_details[[#This Row],[UnitPrice]]*order_details[[#This Row],[Quantity]]*(1-order_details[[#This Row],[Discount]]) -> 26

Sheet products
A1: ProductID | B1: ProductName | C1: SupplierID | D1: CategoryID | E1: QuantityPerUnit | F1: UnitPrice | G1: UnitsInStock | H1: UnitsOnOrder | I1: ReorderLevel | J1: Discontinued | K1: country | L1: Category name | M1: Supplier country
A2: 1 | B2: Chai | C2: 1 | D2: 1 | E2: 10 boxes x 20 bags | F2: 18 | G2: 39 | H2: 0 | I2: 10 | J2: 0 | K2: =_xlfn.XLOOKUP(products[[#This Row],[SupplierID]],suppliers[SupplierID],suppliers[Country]) -> UK | L2: =_xlfn.XLOOKUP(products[[#This Row],[CategoryID]],categories[CategoryID],categories[CategoryName]) -> Beverages | M2: =_xlfn.XLOOKUP(products[[#This Row],[SupplierID]],suppliers[SupplierID],suppliers[Country]) -> UK
A3: 2 | B3: Chang | C3: 1 | D3: 1 | E3: 24 - 12 oz bottles | F3: 19 | G3: 17 | H3: 40 | I3: 25 | J3: 0 | K3: =_xlfn.XLOOKUP(products[[#This Row],[SupplierID]],suppliers[SupplierID],suppliers[Country]) -> UK | L3: =_xlfn.XLOOKUP(products[[#This Row],[CategoryID]],categories[CategoryID],categories[CategoryName]) -> Beverages | M3: =_xlfn.XLOOKUP(products[[#This Row],[SupplierID]],suppliers[SupplierID],suppliers[Country]) -> UK
A4: 3 | B4: Aniseed Syrup | C4: 1 | D4: 2 | E4: 12 - 550 ml bottles | F4: 10 | G4: 13 | H4: 70 | I4: 25 | J4: 0 | K4: =_xlfn.XLOOKUP(products[[#This Row],[SupplierID]],suppliers[SupplierID],suppliers[Country]) -> UK | L4: =_xlfn.XLOOKUP(products[[#This Row],[CategoryID]],categories[CategoryID],categories[CategoryName]) -> Condiments | M4: =_xlfn.XLOOKUP(products[[#This Row],[SupplierID]],suppliers[SupplierID],suppliers[Country]) -> UK
A5: 4 | B5: Chef Anton's Cajun Seasoning | C5: 2 | D5: 2 | E5: 48 - 6 oz jars | F5: 22 | G5: 53 | H5: 0 | I5: 0 | J5: 0 | K5: =_xlfn.XLOOKUP(products[[#This Row],[SupplierID]],suppliers[SupplierID],suppliers[Country]) -> USA | L5: =_xlfn.XLOOKUP(products[[#This Row],[CategoryID]],categories[CategoryID],categories[CategoryName]) -> Condiments | M5: =_xlfn.XLOOKUP(products[[#This Row],[SupplierID]],suppliers[SupplierID],suppliers[Country]) -> USA
A6: 5 | B6: Chef Anton's Gumbo Mix | C6: 2 | D6: 2 | E6: 36 boxes | F6: 21.35 | G6: 0 | H6: 0 | I6: 0 | J6: 1 | K6: =_xlfn.XLOOKUP(products[[#This Row],[SupplierID]],suppliers[SupplierID],suppliers[Country]) -> USA | L6: =_xlfn.XLOOKUP(products[[#This Row],[CategoryID]],categories[CategoryID],categories[CategoryName]) -> Condiments | M6: =_xlfn.XLOOKUP(products[[#This Row],[SupplierID]],suppliers[SupplierID],suppliers[Country]) -> USA
A7: 6 | B7: Grandma's Boysenberry Spread | C7: 3 | D7: 2 | E7: 12 - 8 oz jars | F7: 25 | G7: 120 | H7: 0 | I7: 25 | J7: 0 | K7: =_xlfn.XLOOKUP(products[[#This Row],[SupplierID]],suppliers[SupplierID],suppliers[Country]) -> USA | L7: =_xlfn.XLOOKUP(products[[#This Row],[CategoryID]],categories[CategoryID],categories[CategoryName]) -> Condiments | M7: =_xlfn.XLOOKUP(products[[#This Row],[SupplierID]],suppliers[SupplierID],suppliers[Country]) -> USA
A8: 7 | B8: Uncle Bob's Organic Dried Pears | C8: 3 | D8: 7 | E8: 12 - 1 lb pkgs. | F8: 30 | G8: 15 | H8: 0 | I8: 10 | J8: 0 | K8: =_xlfn.XLOOKUP(products[[#This Row],[SupplierID]],suppliers[SupplierID],suppliers[Country]) -> USA | L8: =_xlfn.XLOOKUP(products[[#This Row],[CategoryID]],categories[CategoryID],categories[CategoryName]) -> Produce | M8: =_xlfn.XLOOKUP(products[[#This Row],[SupplierID]],suppliers[SupplierID],suppliers[Country]) -> USA
A9: 8 | B9: Northwoods Cranberry Sauce | C9: 3 | D9: 2 | E9: 12 - 12 oz jars | F9: 40 | G9: 6 | H9: 0 | I9: 0 | J9: 0 | K9: =_xlfn.XLOOKUP(products[[#This Row],[SupplierID]],suppliers[SupplierID],suppliers[Country]) -> USA | L9: =_xlfn.XLOOKUP(products[[#This Row],[CategoryID]],categories[CategoryID],categories[CategoryName]) -> Condiments | M9: =_xlfn.XLOOKUP(products[[#This Row],[SupplierID]],suppliers[SupplierID],suppliers[Country]) -> USA
A10: 9 | B10: Mishi Kobe Niku | C10: 4 | D10: 6 | E10: 18 - 500 g pkgs. | F10: 97 | G10: 29 | H10: 0 | I10: 0 | J10: 1 | K10: =_xlfn.XLOOKUP(products[[#This Row],[SupplierID]],suppliers[SupplierID],suppliers[Country]) -> Japan | L10: =_xlfn.XLOOKUP(products[[#This Row],[CategoryID]],categories[CategoryID],categories[CategoryName]) -> Meat/Poultry | M10: =_xlfn.XLOOKUP(products[[#This Row],[SupplierID]],suppliers[SupplierID],suppliers[Country]) -> Japan
A11: 10 | B11: Ikura | C11: 4 | D11: 8 | E11: 12 - 200 ml jars | F11: 31 | G11: 31 | H11: 0 | I11: 0 | J11: 0 | K11: =_xlfn.XLOOKUP(products[[#This Row],[SupplierID]],suppliers[SupplierID],suppliers[Country]) -> Japan | L11: =_xlfn.XLOOKUP(products[[#This Row],[CategoryID]],categories[CategoryID],categories[CategoryName]) -> Seafood | M11: =_xlfn.XLOOKUP(products[[#This Row],[SupplierID]],suppliers[SupplierID],suppliers[Country]) -> Japan
A12: 11 | B12: Queso Cabrales | C12: 5 | D12: 4 | E12: 1 kg pkg. | F12: 21 | G12: 22 | H12: 30 | I12: 30 | J12: 0 | K12: =_xlfn.XLOOKUP(products[[#This Row],[SupplierID]],suppliers[SupplierID],suppliers[Country]) -> Spain | L12: =_xlfn.XLOOKUP(products[[#This Row],[CategoryID]],categories[CategoryID],categories[CategoryName]) -> Dairy Products | M12: =_xlfn.XLOOKUP(products[[#This Row],[SupplierID]],suppliers[SupplierID],suppliers[Country]) -> Spain
A13: 12 | B13: Queso Manchego La Pastora | C13: 5 | D13: 4 | E13: 10 - 500 g pkgs. | F13: 38 | G13: 86 | H13: 0 | I13: 0 | J13: 0 | K13: =_xlfn.XLOOKUP(products[[#This Row],[SupplierID]],suppliers[SupplierID],suppliers[Country]) -> Spain | L13: =_xlfn.XLOOKUP(products[[#This Row],[CategoryID]],categories[CategoryID],categories[CategoryName]) -> Dairy Products | M13: =_xlfn.XLOOKUP(products[[#This Row],[SupplierID]],suppliers[SupplierID],suppliers[Country]) -> Spain
... A78: 77 | B78: Original Frankfurter grüne Soße | C78: 12 | D78: 2 | E78: 12 boxes | F78: 13 | G78: 32 | H78: 0 | I78: 15 | J78: 0 | K78: =_xlfn.XLOOKUP(products[[#This Row],[SupplierID]],suppliers[SupplierID],suppliers[Country]) -> Germany | L78: =_xlfn.XLOOKUP(products[[#This Row],[CategoryID]],categories[CategoryID],categories[CategoryName]) -> Condiments | M78: =_xlfn.XLOOKUP(products[[#This Row],[SupplierID]],suppliers[SupplierID],suppliers[Country]) -> Germany

Sheet shippers
A1: ShipperID | B1: CompanyName | C1: Phone
A2: 1 | B2: Speedy Express | C2: (503) 555-9831
A3: 2 | B3: United Package | C3: (503) 555-3199
A4: 3 | B4: Federal Shipping | C4: (503) 555-9931

Sheet suppliers
A1: SupplierID | B1: CompanyName | C1: ContactName | D1: ContactTitle | E1: Address | F1: City | G1: Region | H1: PostalCode | I1: Country | J1: Phone
A2: 1 | B2: Exotic Liquids | C2: Charlotte Cooper | D2: Purchasing Manager | E2: 49 Gilbert St. | F2: London | H2: EC1 4SD | I2: UK | J2: (171) 555-2222
A3: 2 | B3: New Orleans Cajun Delights | C3: Shelley Burke | D3: Order Administrator | E3: P.O. Box 78934 | F3: New Orleans | G3: LA | H3: 70117 | I3: USA | J3: (100) 555-4822
A4: 3 | B4: Grandma Kelly's Homestead | C4: Regina Murphy | D4: Sales Representative | E4: 707 Oxford Rd. | F4: Ann Arbor | G4: MI | H4: 48104 | I4: USA | J4: (313) 555-5735
A5: 4 | B5: Tokyo Traders | C5: Yoshi Nagase | D5: Marketing Manager | E5: 9-8 Sekimai Musashino-shi | F5: Tokyo | H5: 100 | I5: Japan | J5: (03) 3555-5011
A6: 5 | B6: Cooperativa de Quesos 'Las Cabras' | C6: Antonio del Valle Saavedra | D6: Export Administrator | E6: Calle del Rosal 4 | F6: Oviedo | G6: Asturias | H6: 33007 | I6: Spain | J6: (98) 598 76 54
A7: 6 | B7: Mayumi's | C7: Mayumi Ohno | D7: Marketing Representative | E7: 92 Setsuko Chuo-ku | F7: Osaka | H7: 545 | I7: Japan | J7: (06) 431-7877
A8: 7 | B8: Pavlova, Ltd. | C8: Ian Devling | D8: Marketing Manager | E8: 74 Rose St. Moonie Ponds | F8: Melbourne | G8: Victoria | H8: 3058 | I8: Australia | J8: (03) 444-2343
A9: 8 | B9: Specialty Biscuits, Ltd. | C9: Peter Wilson | D9: Sales Representative | E9: 29 King's Way | F9: Manchester | H9: M14 GSD | I9: UK | J9: (161) 555-4448
A10: 9 | B10: PB Knäckebröd AB | C10: Lars Peterson | D10: Sales Agent | E10: Kaloadagatan 13 | F10: Göteborg | H10: S-345 67 | I10: Sweden | J10: 031-987 65 43
A11: 10 | B11: Refrescos Americanas LTDA | C11: Carlos Diaz | D11: Marketing Manager | E11: Av. das Americanas 12.890 | F11: São Paulo | H11: 5442 | I11: Brazil | J11: (11) 555 4640
A12: 11 | B12: Heli Süßwaren GmbH & Co. KG | C12: Petra Winkler | D12: Sales Manager | E12: Tiergartenstraße 5 | F12: Berlin | H12: 10785 | I12: Germany | J12: (010) 9984510
A13: 12 | B13: Plutzer Lebensmittelgroßmärkte AG | C13: Martin Bein | D13: International Marketing Mgr. | E13: Bogenallee 51 | F13: Frankfurt | H13: 60439 | I13: Germany | J13: (069) 992755
A14: 13 | B14: Nord-Ost-Fisch Handelsgesellschaft mbH | C14: Sven Petersen | D14: Coordinator Foreign Markets | E14: Frahmredder 112a | F14: Cuxhaven | H14: 27478 | I14: Germany | J14: (04721) 8713
A15: 14 | B15: Formaggi Fortini s.r.l. | C15: Elio Rossi | D15: Sales Representative | E15: Viale Dante, 75 | F15: Ravenna | H15: 48100 | I15: Italy | J15: (0544) 60323
A16: 15 | B16: Norske Meierier | C16: Beate Vileid | D16: Marketing Manager | E16: Hatlevegen 5 | F16: Sandvika | H16: 1320 | I16: Norway | J16: (0)2-953010
A17: 16 | B17: Bigfoot Breweries | C17: Cheryl Saylor | D17: Regional Account Rep. | E17: 3400 - 8th Avenue Suite 210 | F17: Bend | G17: OR | H17: 97101 | I17: USA | J17: (503) 555-9931
A18: 17 | B18: Svensk Sjöföda AB | C18: Michael Björn | D18: Sales Representative | E18: Brovallavägen 231 | F18: Stockholm | H18: S-123 45 | I18: Sweden | J18: 08-123 45 67
A19: 18 | B19: Aux joyeux ecclésiastiques | C19: Guylène Nodier | D19: Sales Manager | E19: 203, Rue des Francs-Bourgeois | F19: Paris | H19: 75004 | I19: France | J19: (1) 03.83.00.68
A20: 19 | B20: New England Seafood Cannery | C20: Robb Merchant | D20: Wholesale Account Agent | E20: Order Processing Dept. 2100 Paul Revere Blvd. | F20: Boston | G20: MA | H20: 02134 | I20: USA | J20: (617) 555-3267
A21: 20 | B21: Leka Trading | C21: Chandra Leka | D21: Owner | E21: 471 Serangoon Loop, Suite #402 | F21: Singapore | H21: 0512 | I21: Singapore | J21: 555-8787
A22: 21 | B22: Lyngbysild | C22: Niels Petersen | D22: Sales Manager | E22: Lyngbysild Fiskebakken 10 | F22: Lyngby | H22: 2800 | I22: Denmark | J22: 43844108
A23: 22 | B23: Zaanse Snoepfabriek | C23: Dirk Luchte | D23: Accounting Manager | E23: Verkoop Rijnweg 22 | F23: Zaandam | H23: 9999 ZZ | I23: Netherlands | J23: (12345) 1212
A24: 23 | B24: Karkki Oy | C24: Anne Heikkonen | D24: Product Manager | E24: Valtakatu 12 | F24: Lappeenranta | H24: 53120 | I24: Finland | J24: (953) 10956
A25: 24 | B25: G'day, Mate | C25: Wendy Mackenzie | D25: Sales Representative | E25: 170 Prince Edward Parade Hunter's Hill | F25: Sydney | G25: NSW | H25: 2042 | I25: Australia | J25: (02) 555-5914
A26: 25 | B26: Ma Maison | C26: Jean-Guy Lauzon | D26: Marketing Manager | E26: 2960 Rue St. Laurent | F26: Montréal | G26: Québec | H26: H1J 1C3 | I26: Canada | J26: (514) 555-9022
A27: 26 | B27: Pasta Buttini s.r.l. | C27: Giovanni Giudici | D27: Order Administrator | E27: Via dei Gelsomini, 153 | F27: Salerno | H27: 84100 | I27: Italy | J27: (089) 6547665
A28: 27 | B28: Escargots Nouveaux | C28: Marie Delamare | D28: Sales Manager | E28: 22, rue H. Voiron | F28: Montceau | H28: 71300 | I28: France | J28: 85.57.00.07
A29: 28 | B29: Gai pâturage | C29: Eliane Noz | D29: Sales Representative | E29: Bat. B 3, rue des Alpes | F29: Annecy | H29: 74000 | I29: France | J29: 38.76.98.06
A30: 29 | B30: Forêts d'érables | C30: Chantal Goulet | D30: Accounting Manager | E30: 148 rue Chasseur | F30: Ste-Hyacinthe | G30: Québec | H30: J2S 7S8 | I30: Canada | J30: (514) 555-2955
